Workbook

Sheet Assessment Sheet
A1: ID | B1: Chapter | C1: Section | D1: Enforcement Component | E1: Requirement | F1: Minimum level | G1: L1 | H1: L2 | I1: L3 | J1: Applicability | K1: Status | L1: Evidence and Notes | M1: Owner | N1: Planned Completion | O1: Level No.
A2: V1.1.1 | B2: V1 Identity and Authentication | C2: V1.1 User Authentication | D2: Identity layer | E2: The platform and all its channels shall allow login only through the enterprise IdP (OIDC or SAML) and shall not provide independent local accounts, except for the break-glass accounts specified in V10.5 | F2: L1 | G2: ✓ | H2: ✓ | I2: ✓ | J2: All platforms | K2: Not assessed | O2: =VALUE(RIGHT(F2,1)) -> 1
A3: V1.1.2 | B3: V1 Identity and Authentication | C3: V1.1 User Authentication | D3: Identity layer | E3: Users and groups shall be synchronized through SCIM or an equivalent mechanism, and users disabled in the IdP shall be disabled in the platform in sync | F3: L2 | H3: ✓ | I3: ✓ | J3: All platforms | K3: Not assessed | O3: =VALUE(RIGHT(F3,1)) -> 2
A4: V1.1.3 | B4: V1 Identity and Authentication | C4: V1.1 User Authentication | D4: Identity layer | E4: The authentication time and authentication strength issued by the IdP shall be retained in the user session for use in the step-up authentication decisions of V3.5 | F4: L2 | H4: ✓ | I4: ✓ | J4: All platforms | K4: Not assessed | O4: =VALUE(RIGHT(F4,1)) -> 2
A5: V1.1.4 | B5: V1 Identity and Authentication | C5: V1.1 User Authentication | D5: Identity layer | E5: Credentials used to invoke agents through an API (such as API keys and personal access tokens) shall be bound to a specific user or non-human identity in the enterprise IdP, shall have an expiration time and a permission scope set, and shall be revoked automatically when the identity is disabled | F5: L1 | G5: ✓ | H5: ✓ | I5: ✓ | J5: All platforms | K5: Not assessed | O5: =VALUE(RIGHT(F5,1)) -> 1
A6: V1.2.1 | B6: V1 Identity and Authentication | C6: V1.2 Channel Identity Mapping | D6: Interaction channel | E6: A channel account shall be bound to an enterprise identity through a one-time SSO login before it can invoke an agent | F6: L1 | G6: ✓ | H6: ✓ | I6: ✓ | J6: Platforms that support third-party channels such as IM, email, and browser extensions | K6: Not assessed | O6: =VALUE(RIGHT(F6,1)) -> 1
A7: V1.2.2 | B7: V1 Identity and Authentication | C7: V1.2 Channel Identity Mapping | D7: Interaction channel | E7: The SSO binding result shall be the sole basis for identifying a channel account. Matching by nickname, display name, or email string is not permitted. The email channel follows V1.2.6. | F7: L1 | G7: ✓ | H7: ✓ | I7: ✓ | J7: Platforms that support third-party channels such as IM, email, and browser extensions | K7: Not assessed | O7: =VALUE(RIGHT(F7,1)) -> 1
A8: V1.2.3 | B8: V1 Identity and Authentication | C8: V1.2 Channel Identity Mapping | D8: Interaction channel | E8: When a user is disabled in the IdP, all of that user's channel bindings shall be invalidated in sync | F8: L2 | H8: ✓ | I8: ✓ | J8: Platforms that support third-party channels such as IM, email, and browser extensions | K8: Not assessed | O8: =VALUE(RIGHT(F8,1)) -> 2
A9: V1.2.4 | B9: V1 Identity and Authentication | C9: V1.2 Channel Identity Mapping | D9: Interaction channel | E9: Accounts from external visitors and from cross-organization shared channels shall be identified, and the agents and capabilities available to them shall be restricted separately | F9: L2 | H9: ✓ | I9: ✓ | J9: Platforms that support third-party channels such as IM, email, and browser extensions | K9: Not assessed | O9: =VALUE(RIGHT(F9,1)) -> 2
A10: V1.2.5 | B10: V1 Identity and Authentication | C10: V1.2 Channel Identity Mapping | D10: Interaction channel | E10: When a high-risk operation is triggered within a channel, the user shall be required to complete step-up authentication through the enterprise IdP | F10: L2 | H10: ✓ | I10: ✓ | J10: Platforms that support third-party channels such as IM, email, and browser extensions | K10: Not assessed | O10: =VALUE(RIGHT(F10,1)) -> 2
A11: V1.2.6 | B11: V1 Identity and Authentication | C11: V1.2 Channel Identity Mapping | D11: Interaction channel | E11: The email channel shall accept only email that passes DMARC verification (SPF or DKIM passing and aligned with the From domain). Senders from external domains shall not be able to trigger operations on behalf of a user. | F11: L1 | G11: ✓ | H11: ✓ | I11: ✓ | J11: Platforms that support third-party channels such as IM, email, and browser extensions | K11: Not assessed | O11: =VALUE(RIGHT(F11,1)) -> 1
A12: V1.3.1 | B12: V1 Identity and Authentication | C12: V1.3 Agent Identity | D12: Identity layer | E12: Each agent shall have a unique identifier issued by the platform. The platform shall not accept identities self-reported by the agent. | F12: L1 | G12: ✓ | H12: ✓ | I12: ✓ | J12: All platforms | K12: Not assessed | O12: =VALUE(RIGHT(F12,1)) -> 1
A13: V1.3.2 | B13: V1 Identity and Authentication | C13: V1.3 Agent Identity | D13: Identity layer | E13: An independent non-human identity shall be established in the enterprise directory for each autonomous agent. No employee's personal account shall be used. | F13: L1 | G13: ✓ | H13: ✓ | I13: ✓ | J13: All platforms | K13: Not assessed | O13: =VALUE(RIGHT(F13,1)) -> 1
A14: V1.3.3 | B14: V1 Identity and Authentication | C14: V1.3 Agent Identity | D14: Downstream systems | E14: When an autonomous agent accesses downstream systems, it shall use the identity established under V1.3.2, and the principal recorded in downstream logs shall be that agent | F14: L2 | H14: ✓ | I14: ✓ | J14: All platforms | K14: Not assessed | O14: =VALUE(RIGHT(F14,1)) -> 2
A15: V1.3.4 | B15: V1 Identity and Authentication | C15: V1.3 Agent Identity | D15: Identity layer | E15: When an autonomous agent accesses downstream systems, it shall use short-lived tokens and shall not use long-term static keys | F15: L2 | H15: ✓ | I15: ✓ | J15: All platforms | K15: Not assessed | O15: =VALUE(RIGHT(F15,1)) -> 2
A16: V1.3.5 | B16: V1 Identity and Authentication | C16: V1.3 Agent Identity | D16: Identity layer | E16: The keys and certificates of an autonomous agent shall have processes for issuance, rotation, and revocation, and the rotation period shall have an upper limit | F16: L2 | H16: ✓ | I16: ✓ | J16: All platforms | K16: Not assessed | O16: =VALUE(RIGHT(F16,1)) -> 2
A17: V1.4.1 | B17: V1 Identity and Authentication | C17: V1.4 Workload Identity | D17: Identity layer | E17: The platform shall issue a short-lived workload identity to the execution instance of each session and bind it to that instance | F17: L1 | G17: ✓ | H17: ✓ | I17: ✓ | J17: Platforms that assign an independent execution instance (such as a container, sandbox, or virtual machine) to each session | K17: Not assessed | O17: =VALUE(RIGHT(F17,1)) -> 1
A18: V1.4.2 | B18: V1 Identity and Authentication | C18: V1.4 Workload Identity | D18: Harness | E18: The credentials of the workload identity shall be invisible to the model and shall not enter the context or tool return values | F18: L1 | G18: ✓ | H18: ✓ | I18: ✓ | J18: Platforms that assign an independent execution instance (such as a container, sandbox, or virtual machine) to each session | K18: Not assessed | O18: =VALUE(RIGHT(F18,1)) -> 1
A19: V1.4.3 | B19: V1 Identity and Authentication | C19: V1.4 Workload Identity | D19: Egress gateway | E19: The egress gateway shall determine the user and agent solely from the workload identity and shall ignore user or agent identifiers self-reported in the request | F19: L1 | G19: ✓ | H19: ✓ | I19: ✓ | J19: Platforms that assign an independent execution instance (such as a container, sandbox, or virtual machine) to each session | K19: Not assessed | O19: =VALUE(RIGHT(F19,1)) -> 1
A20: V1.4.4 | B20: V1 Identity and Authentication | C20: V1.4 Workload Identity | D20: Identity layer | E20: When a session ends or an execution instance is destroyed, the corresponding workload identity shall be revoked immediately | F20: L2 | H20: ✓ | I20: ✓ | J20: Platforms that assign an independent execution instance (such as a container, sandbox, or virtual machine) to each session | K20: Not assessed | O20: =VALUE(RIGHT(F20,1)) -> 2
A21: V1.4.5 | B21: V1 Identity and Authentication | C21: V1.4 Workload Identity | D21: Identity layer | E21: Before issuing a workload identity, the platform shall perform workload attestation on the execution instance (such as node attestation and workload attestation in SPIFFE/SPIRE). The identity shall not be issued if attestation fails. | F21: L3 | I21: ✓ | J21: Platforms that assign an independent execution instance (such as a container, sandbox, or virtual machine) to each session | K21: Not assessed | O21: =VALUE(RIGHT(F21,1)) -> 3
A22: V1.5.1 | B22: V1 Identity and Authentication | C22: V1.5 External Principals | D22: Identity layer | E22: External principals shall be accessed through identity federation, and no shared account shall be created for them | F22: L2 | H22: ✓ | I22: ✓ | J22: Platforms that open agent capabilities to customers or partners | K22: Not assessed | O22: =VALUE(RIGHT(F22,1)) -> 2
A23: V1.5.2 | B23: V1 Identity and Authentication | C23: V1.5 External Principals | D23: Policy decision point | E23: External principals shall have access only to the workspaces and interfaces made available to them | F23: L1 | G23: ✓ | H23: ✓ | I23: ✓ | J23: Platforms that open agent capabilities to customers or partners | K23: Not assessed | O23: =VALUE(RIGHT(F23,1)) -> 1
A24: V1.5.3 | B24: V1 Identity and Authentication | C24: V1.5 External Principals | D24: Audit | E24: Invocations by external principals shall be recorded separately in the audit log and shall be filterable by external organization | F24: L2 | H24: ✓ | I24: ✓ | J24: Platforms that open agent capabilities to customers or partners | K24: Not assessed | O24: =VALUE(RIGHT(F24,1)) -> 2
A25: V2.1.1 | B25: V2 Delegation and Effective Permissions | C25: V2.1 Access on Behalf of a User | D25: Egress gateway | E25: When the user is present, an agent accessing downstream systems shall carry the identity of the initiating user, and the downstream system shall make its authorization decision based on that user. Downstream systems that do not support user-level authorization decisions are handled under V4.4. | F25: L1 | G25: ✓ | H25: ✓ | I25: ✓ | J25: All platforms | K25: Not assessed | O25: =VALUE(RIGHT(F25,1)) -> 1
A26: V2.1.2 | B26: V2 Delegation and Effective Permissions | C26: V2.1 Access on Behalf of a User | D26: Egress gateway | E26: Shared credentials with higher permissions than the initiating user shall not be used to access downstream systems on the user's behalf. Downstream systems that support only shared static credentials are handled by compensating controls under V4.4. | F26: L1 | G26: ✓ | H26: ✓ | I26: ✓ | J26: All platforms | K26: Not assessed | O26: =VALUE(RIGHT(F26,1)) -> 1
A27: V2.1.3 | B27: V2 Delegation and Effective Permissions | C27: V2.1 Access on Behalf of a User | D27: Identity layer | E27: Downstream tokens shall identify both the initiating user and the executing agent (such as the act claim in RFC 8693) | F27: L2 | H27: ✓ | I27: ✓ | J27: All platforms | K27: Not assessed | O27: =VALUE(RIGHT(F27,1)) -> 2
A28: V2.2.1 | B28: V2 Delegation and Effective Permissions | C28: V2.2 Effective Permissions | D28: Policy decision point | E28: The effective permissions of each invocation shall be the intersection of the user's permissions and the agent authorization scope | F28: L1 | G28: ✓ | H28: ✓ | I28: ✓ | J28: All platforms | K28: Not assessed | O28: =VALUE(RIGHT(F28,1)) -> 1
A29: V2.2.2 | B29: V2 Delegation and Effective Permissions | C29: V2.2 Effective Permissions | D29: Policy decision point | E29: Effective permissions shall be computed by the policy decision point and shall not depend on the system prompt or on the model's judgment | F29: L1 | G29: ✓ | H29: ✓ | I29: ✓ | J29: All platforms | K29: Not assessed | O29: =VALUE(RIGHT(F29,1)) -> 1
A30: V2.2.3 | B30: V2 Delegation and Effective Permissions | C30: V2.2 Effective Permissions | D30: Policy decision point | E30: At the start of a task, the required tool and data scope shall be declared. During execution, only permissions within the declared scope shall be granted. The declaration is provided by the user or by agent configuration, and any scope proposed by the model shall take effect only after user confirmation. | F30: L2 | H30: ✓ | I30: ✓ | J30: All platforms | K30: Not assessed | O30: =VALUE(RIGHT(F30,1)) -> 2
A31: V2.2.4 | B31: V2 Delegation and Effective Permissions | C31: V2.2 Effective Permissions | D31: Policy decision point | E31: Invocations beyond the task's declared scope shall be rejected or require approval | F31: L2 | H31: ✓ | I31: ✓ | J31: All platforms | K31: Not assessed | O31: =VALUE(RIGHT(F31,1)) -> 2
A32: V2.2.5 | B32: V2 Delegation and Effective Permissions | C32: V2.2 Effective Permissions | D32: Policy decision point | E32: Effective permissions shall be recomputed on each tool invocation and shall not reuse the authorization result from the start of the session | F32: L2 | H32: ✓ | I32: ✓ | J32: All platforms | K32: Not assessed | O32: =VALUE(RIGHT(F32,1)) -> 2
A33: V2.2.6 | B33: V2 Delegation and Effective Permissions | C33: V2.2 Effective Permissions | D33: Policy decision point | E33: Authorization for high-risk operations shall be refined to specific resources and parameters (for example, using RFC 9396 Rich Authorization Requests to describe the authorization details) and shall not grant only coarse-grained roles | F33: L3 | I33: ✓ | J33: All platforms | K33: Not assessed | O33: =VALUE(RIGHT(F33,1)) -> 3
A34: V2.3.1 | B34: V2 Delegation and Effective Permissions | C34: V2.3 Offline Delegated Tasks | D34: Policy decision point | E34: An offline delegated task shall be rooted in its creating user. The permission upper limit shall be fixed at creation and can only be narrowed thereafter. | F34: L1 | G34: ✓ | H34: ✓ | I34: ✓ | J34: Platforms that support scheduled or long-running tasks | K34: Not assessed | O34: =VALUE(RIGHT(F34,1)) -> 1
A35: V2.3.2 | B35: V2 Delegation and Effective Permissions | C35: V2.3 Offline Delegated Tasks | D35: Policy decision point | E35: The account status and current permissions of the creating user shall be rechecked before each run | F35: L1 | G35: ✓ | H35: ✓ | I35: ✓ | J35: Platforms that support scheduled or long-running tasks | K35: Not assessed | O35: =VALUE(RIGHT(F35,1)) -> 1
A36: V2.3.3 | B36: V2 Delegation and Effective Permissions | C36: V2.3 Offline Delegated Tasks | D36: Harness | E36: The scheduler shall store only task identifiers and shall not store user credentials or directly usable tokens | F36: L1 | G36: ✓ | H36: ✓ | I36: ✓ | J36: Platforms that support scheduled or long-running tasks | K36: Not assessed | O36: =VALUE(RIGHT(F36,1)) -> 1
A37: V2.3.4 | B37: V2 Delegation and Effective Permissions | C37: V2.3 Offline Delegated Tasks | D37: Management plane | E37: When the creating user is disabled, their offline delegated tasks shall stop automatically, and the owner of the agent shall be notified | F37: L2 | H37: ✓ | I37: ✓ | J37: Platforms that support scheduled or long-running tasks | K37: Not assessed | O37: =VALUE(RIGHT(F37,1)) -> 2
A38: V2.3.5 | B38: V2 Delegation and Effective Permissions | C38: V2.3 Offline Delegated Tasks | D38: Management plane | E38: For tasks that must continue running after the creating user leaves or changes roles, the tasks shall be converted to autonomous agents and reauthorized through approval before the user's account is disabled | F38: L2 | H38: ✓ | I38: ✓ | J38: Platforms that support scheduled or long-running tasks | K38: Not assessed | O38: =VALUE(RIGHT(F38,1)) -> 2
A39: V2.3.6 | B39: V2 Delegation and Effective Permissions | C39: V2.3 Offline Delegated Tasks | D39: Policy decision point | E39: The authorization for an offline delegated task shall have an expiration time, after which the creating user must reconfirm it | F39: L2 | H39: ✓ | I39: ✓ | J39: Platforms that support scheduled or long-running tasks | K39: Not assessed | O39: =VALUE(RIGHT(F39,1)) -> 2
A40: V2.4.1 | B40: V2 Delegation and Effective Permissions | C40: V2.4 Inter-Agent Delegation | D40: Policy decision point | E40: The effective permissions of a downstream agent shall not exceed the permissions of the initiating user or the delegation scope granted by the upstream agent. The initiating user shall not obtain, through a downstream agent, permissions that the user does not hold. | F40: L1 | G40: ✓ | H40: ✓ | I40: ✓ | J40: Platforms that support multi-agent collaboration or sub-agents | K40: Not assessed | O40: =VALUE(RIGHT(F40,1)) -> 1
A41: V2.4.2 | B41: V2 Delegation and Effective Permissions | C41: V2.4 Inter-Agent Delegation | D41: Harness | E41: For sub-agents derived by the harness, the available tools and permissions shall be a subset of those of the parent agent | F41: L2 | H41: ✓ | I41: ✓ | J41: Platforms that support multi-agent collaboration or sub-agents | K41: Not assessed | O41: =VALUE(RIGHT(F41,1)) -> 2
A42: V2.4.3 | B42: V2 Delegation and Effective Permissions | C42: V2.4 Inter-Agent Delegation | D42: Policy decision point | E42: The delegation chain shall be constructed and recorded by the platform. Identity assertions not signed by the platform or by a trusted authorization server shall not be accepted. | F42: L1 | G42: ✓ | H42: ✓ | I42: ✓ | J42: Platforms that support multi-agent collaboration or sub-agents | K42: Not assessed | O42: =VALUE(RIGHT(F42,1)) -> 1
A43: V2.4.4 | B43: V2 Delegation and Effective Permissions | C43: V2.4 Inter-Agent Delegation | D43: Policy decision point | E43: Which agents may invoke which other agents shall be explicitly configured. Invocations that are not configured shall be rejected. | F43: L2 | H43: ✓ | I43: ✓ | J43: Platforms that support multi-agent collaboration or sub-agents | K43: Not assessed | O43: =VALUE(RIGHT(F43,1)) -> 2
A44: V2.4.5 | B44: V2 Delegation and Effective Permissions | C44: V2.4 Inter-Agent Delegation | D44: Policy decision point | E44: The depth of the delegation chain shall be limited, and circular invocations shall be detected and blocked | F44: L2 | H44: ✓ | I44: ✓ | J44: Platforms that support multi-agent collaboration or sub-agents | K44: Not assessed | O44: =VALUE(RIGHT(F44,1)) -> 2
A45: V2.4.6 | B45: V2 Delegation and Effective Permissions | C45: V2.4 Inter-Agent Delegation | D45: Identity layer | E45: In multi-hop delegation, downstream tokens shall carry the complete executor chain (such as nested act claims in RFC 8693) so that downstream systems can make authorization decisions accordingly | F45: L2 | H45: ✓ | I45: ✓ | J45: Platforms that support multi-agent collaboration or sub-agents | K45: Not assessed | O45: =VALUE(RIGHT(F45,1)) -> 2
A46: V2.4.7 | B46: V2 Delegation and Effective Permissions | C46: V2.4 Inter-Agent Delegation | D46: Identity layer | E46: For cross-service invocations within the same trust domain, tokens carrying user, agent, and task context shall be propagated along the call chain (such as the Transaction Tokens draft), so that downstream systems can make authorization decisions accordingly | F46: L3 | I46: ✓ | J46: Platforms that support multi-agent collaboration or sub-agents | K46: Not assessed | O46: =VALUE(RIGHT(F46,1)) -> 3
A47: V2.5.1 | B47: V2 Delegation and Effective Permissions | C47: V2.5 Inter-User Delegation and Temporary Privilege Elevation | D47: Policy decision point | E47: When a user permits others to operate the user's agent on their behalf (for example, an assistant acting for a manager), the delegation relationship shall be explicitly registered, with a defined scope and period | F47: L2 | H47: ✓ | I47: ✓ | J47: Platforms that let users operate agents on behalf of others, or that support temporary privilege elevation for agents | K47: Not assessed | O47: =VALUE(RIGHT(F47,1)) -> 2
A48: V2.5.2 | B48: V2 Delegation and Effective Permissions | C48: V2.5 Inter-User Delegation and Temporary Privilege Elevation | D48: Audit | E48: When operating on behalf of another person, audit shall record both the principal and the person who actually performed the operation | F48: L2 | H48: ✓ | I48: ✓ | J48: Platforms that let users operate agents on behalf of others, or that support temporary privilege elevation for agents | K48: Not assessed | O48: =VALUE(RIGHT(F48,1)) -> 2
A49: V2.5.3 | B49: V2 Delegation and Effective Permissions | C49: V2.5 Inter-User Delegation and Temporary Privilege Elevation | D49: Policy decision point | E49: When an agent requires permissions beyond its authorization scope, they shall be granted for a limited time through request and approval, and they shall be withdrawn automatically upon expiry | F49: L3 | I49: ✓ | J49: Platforms that let users operate agents on behalf of others, or that support temporary privilege elevation for agents | K49: Not assessed | O49: =VALUE(RIGHT(F49,1)) -> 3
A50: V2.6.1 | B50: V2 Delegation and Effective Permissions | C50: V2.6 Event-Triggered Authorization | D50: Interaction channel | E50: Inbound events shall have their signatures and sources verified, and events that fail verification shall be rejected | F50: L1 | G50: ✓ | H50: ✓ | I50: ✓ | J50: Platforms that support agents triggered by events such as webhooks, alerts, or tickets | K50: Not assessed | O50: =VALUE(RIGHT(F50,1)) -> 1
A51: V2.6.2 | B51: V2 Delegation and Effective Permissions | C51: V2.6 Event-Triggered Authorization | D51: Management plane | E51: Each trigger rule shall be bound to an execution identity, namely the identity of an autonomous agent or the identity of the person who configured the rule | F51: L1 | G51: ✓ | H51: ✓ | I51: ✓ | J51: Platforms that support agents triggered by events such as webhooks, alerts, or tickets | K51: Not assessed | O51: =VALUE(RIGHT(F51,1)) -> 1
A52: V2.6.3 | B52: V2 Delegation and Effective Permissions | C52: V2.6 Event-Triggered Authorization | D52: Audit | E52: The creation and modification of trigger rules shall be recorded in the audit log and shall identify the person who configured them | F52: L2 | H52: ✓ | I52: ✓ | J52: Platforms that support agents triggered by events such as webhooks, alerts, or tickets | K52: Not assessed | O52: =VALUE(RIGHT(F52,1)) -> 2
A53: V3.1.1 | B53: V3 Authorization Decisions | C53: V3.1 Operation Risk Classification | D53: Policy decision point | E53: Each tool shall be labeled with an operation category (distinguishing at least read, write, delete, outbound transfer, fund operation, and production change) and a risk level | F53: L1 | G53: ✓ | H53: ✓ | I53: ✓ | J53: All platforms | K53: Not assessed | O53: =VALUE(RIGHT(F53,1)) -> 1
A54: V3.1.2 | B54: V3 Authorization Decisions | C54: V3.1 Operation Risk Classification | D54: Policy decision point | E54: The risk level shall be determined by the platform based on the tool and its parameters, and shall not be based on the risk assessment given by the model | F54: L1 | G54: ✓ | H54: ✓ | I54: ✓ | J54: All platforms | K54: Not assessed | O54: =VALUE(RIGHT(F54,1)) -> 1
A55: V3.1.3 | B55: V3 Authorization Decisions | C55: V3.1 Operation Risk Classification | D55: Policy decision point | E55: Each risk level shall correspond to a defined disposition, such as automatic execution, after-the-fact notification, prior approval, step-up authentication, or rejection | F55: L1 | G55: ✓ | H55: ✓ | I55: ✓ | J55: All platforms | K55: Not assessed | O55: =VALUE(RIGHT(F55,1)) -> 1
A56: V3.1.4 | B56: V3 Authorization Decisions | C56: V3.1 Operation Risk Classification | D56: Policy decision point | E56: The same tool, under parameters with different scopes of impact (such as deleting one record versus bulk deletion), shall be able to fall into different levels | F56: L2 | H56: ✓ | I56: ✓ | J56: All platforms | K56: Not assessed | O56: =VALUE(RIGHT(F56,1)) -> 2
A57: V3.2.1 | B57: V3 Authorization Decisions | C57: V3.2 Pre-Invocation Validation for Tool Calls | D57: Harness | E57: Every tool invocation shall pass a policy check before execution. The check shall run in a component that the agent cannot modify (a platform-hosted harness, the policy decision point, or the egress gateway). Authorization decisions shall not be based on the output of the model used by the agent being checked. | F57: L1 | G57: ✓ | H57: ✓ | I57: ✓ | J57: All platforms | K57: Not assessed | O57: =VALUE(RIGHT(F57,1)) -> 1
A58: V3.2.2 | B58: V3 Authorization Decisions | C58: V3.2 Pre-Invocation Validation for Tool Calls | D58: Harness | E58: Security constraints shall be enforced by the policy enforcement point (the harness or the egress gateway) according to the decisions of the policy decision point, and they shall not exist only in the system prompt | F58: L2 | H58: ✓ | I58: ✓ | J58: All platforms | K58: Not assessed | O58: =VALUE(RIGHT(F58,1)) -> 2
A59: V3.2.3 | B59: V3 Authorization Decisions | C59: V3.2 Pre-Invocation Validation for Tool Calls | D59: Harness | E59: The policies and hooks for pre-execution checks shall be distributed by the platform, and the agent itself shall not be able to modify or bypass them | F59: L2 | H59: ✓ | I59: ✓ | J59: All platforms | K59: Not assessed | O59: =VALUE(RIGHT(F59,1)) -> 2
A60: V3.2.4 | B60: V3 Authorization Decisions | C60: V3.2 Pre-Invocation Validation for Tool Calls | D60: Harness | E60: When a policy check errors or times out, the default shall be to deny | F60: L1 | G60: ✓ | H60: ✓ | I60: ✓ | J60: All platforms | K60: Not assessed | O60: =VALUE(RIGHT(F60,1)) -> 1
A61: V3.2.5 | B61: V3 Authorization Decisions | C61: V3.2 Pre-Invocation Validation for Tool Calls | D61: Policy decision point | E61: The policy decision point shall interact with the policy enforcement point through a standardized authorization interface (such as OpenID AuthZEN) to facilitate replacement of the policy engine | F61: L3 | I61: ✓ | J61: All platforms | K61: Not assessed | O61: =VALUE(RIGHT(F61,1)) -> 3
A62: V3.3.1 | B62: V3 Authorization Decisions | C62: V3.3 Tool Exposure | D62: Harness | E62: The tool list provided to the model shall be filtered by current effective permissions, so that the model cannot see tools it is not authorized to use | F62: L2 | H62: ✓ | I62: ✓ | J62: All platforms | K62: Not assessed | O62: =VALUE(RIGHT(F62,1)) -> 2
A63: V3.3.2 | B63: V3 Authorization Decisions | C63: V3.3 Tool Exposure | D63: Harness | E63: Beyond trimming the tool list, V3.2 validation shall still be applied before execution | F63: L2 | H63: ✓ | I63: ✓ | J63: All platforms | K63: Not assessed | O63: =VALUE(RIGHT(F63,1)) -> 2
A64: V3.4.1 | B64: V3 Authorization Decisions | C64: V3.4 Human Approval | D64: Harness | E64: High-risk operations shall be approved, before execution, by a person authorized to approve them. Operations not subject to dual control may be approved by the initiating user. | F64: L1 | G64: ✓ | H64: ✓ | I64: ✓ | J64: All platforms | K64: Not assessed | O64: =VALUE(RIGHT(F64,1)) -> 1
A65: V3.4.2 | B65: V3 Authorization Decisions | C65: V3.4 Human Approval | D65: Harness | E65: Approval content shall be generated by the platform from the actual invocation parameters and shall not use a summary written by the model | F65: L1 | G65: ✓ | H65: ✓ | I65: ✓ | J65: All platforms | K65: Not assessed | O65: =VALUE(RIGHT(F65,1)) -> 1
A66: V3.4.3 | B66: V3 Authorization Decisions | C66: V3.4 Human Approval | D66: Harness | E66: At execution, the actual parameters shall be verified to match those at approval, and execution shall be rejected if they do not match. For invocations executed under a pre-approved plan per V3.4.6, the invocation shall be verified to be within the plan's scope. | F66: L1 | G66: ✓ | H66: ✓ | I66: ✓ | J66: All platforms | K66: Not assessed | O66: =VALUE(RIGHT(F66,1)) -> 1
A67: V3.4.4 | B67: V3 Authorization Decisions | C67: V3.4 Human Approval | D67: Harness | E67: Approvals shall have a validity period, and an approval request that expires without a decision shall be treated as rejected | F67: L2 | H67: ✓ | I67: ✓ | J67: All platforms | K67: Not assessed | O67: =VALUE(RIGHT(F67,1)) -> 2
A68: V3.4.5 | B68: V3 Authorization Decisions | C68: V3.4 Human Approval | D68: Harness | E68: The frequency of approval requests shall be limited and similar requests shall be merged to prevent approval fatigue | F68: L2 | H68: ✓ | I68: ✓ | J68: All platforms | K68: Not assessed | O68: =VALUE(RIGHT(F68,1)) -> 2
A69: V3.4.6 | B69: V3 Authorization Decisions | C69: V3.4 Human Approval | D69: Policy decision point | E69: The platform shall support pre-approved execution plans that specify tools, resource scope, and limits. Operations within the plan's scope are not approved individually each time. Operations exceeding the scope shall be aborted and reapproved. | F69: L2 | H69: ✓ | I69: ✓ | J69: All platforms | K69: Not assessed | O69: =VALUE(RIGHT(F69,1)) -> 2
A70: V3.5.1 | B70: V3 Authorization Decisions | C70: V3.5 Step-Up Authentication and Continuous Access Evaluation | D70: Identity layer | E70: Operations such as fund transfers, production changes, and bulk deletion shall require the user to complete step-up authentication (such as re-completing MFA) | F70: L2 | H70: ✓ | I70: ✓ | J70: All platforms | K70: Not assessed | O70: =VALUE(RIGHT(F70,1)) -> 2
A71: V3.5.2 | B71: V3 Authorization Decisions | C71: V3.5 Step-Up Authentication and Continuous Access Evaluation | D71: Policy decision point | E71: The platform shall receive session risk signals from the IdP (such as CAEP). When risk rises, it shall lower the level of operations the agent may perform or suspend the agent. | F71: L3 | I71: ✓ | J71: All platforms | K71: Not assessed | O71: =VALUE(RIGHT(F71,1)) -> 3
A72: V3.6.1 | B72: V3 Authorization Decisions | C72: V3.6 Separation of Duties | D72: Management plane | E72: Mutually exclusive duties (such as submission and approval, or development and release) shall not be assigned to the same agent | F72: L2 | H72: ✓ | I72: ✓ | J72: All platforms | K72: Not assessed | O72: =VALUE(RIGHT(F72,1)) -> 2
A73: V3.6.2 | B73: V3 Authorization Decisions | C73: V3.6 Separation of Duties | D73: Policy decision point | E73: For operations that require dual control under separation of duties (such as payments, production changes, and permission grants), the approver shall not be the initiator, nor an agent acting on the initiator's behalf | F73: L2 | H73: ✓ | I73: ✓ | J73: All platforms | K73: Not assessed | O73: =VALUE(RIGHT(F73,1)) -> 2
A74: V3.7.1 | B74: V3 Authorization Decisions | C74: V3.7 Persistent Operations | D74: Harness | E74: When an agent creates or modifies scheduled tasks, trigger rules, webhooks, forwarding rules, or skills, such changes shall take effect only after user approval | F74: L1 | G74: ✓ | H74: ✓ | I74: ✓ | J74: All platforms | K74: Not assessed | O74: =VALUE(RIGHT(F74,1)) -> 1
A75: V3.7.2 | B75: V3 Authorization Decisions | C75: V3.7 Persistent Operations | D75: Management plane | E75: The management plane shall be able to centrally list all persistent objects created by an agent and indicate the source of their creation | F75: L2 | H75: ✓ | I75: ✓ | J75: All platforms | K75: Not assessed | O75: =VALUE(RIGHT(F75,1)) -> 2
A76: V3.8.1 | B76: V3 Authorization Decisions | C76: V3.8 Quantity, Rate, and Quota | D76: Egress gateway | E76: Rate, bulk, and export limits shall be set by user, agent, and operation type | F76: L2 | H76: ✓ | I76: ✓ | J76: All platforms | K76: Not assessed | O76: =VALUE(RIGHT(F76,1)) -> 2
A77: V3.8.2 | B77: V3 Authorization Decisions | C77: V3.8 Quantity, Rate, and Quota | D77: Egress gateway | E77: Requests exceeding limits shall be blocked and alerted | F77: L2 | H77: ✓ | I77: ✓ | J77: All platforms | K77: Not assessed | O77: =VALUE(RIGHT(F77,1)) -> 2
A78: V3.8.3 | B78: V3 Authorization Decisions | C78: V3.8 Quantity, Rate, and Quota | D78: Harness | E78: Model invocation budgets shall be set by department, user, or agent. When a budget is exceeded, the invocations shall be paused or require approval. | F78: L2 | H78: ✓ | I78: ✓ | J78: All platforms | K78: Not assessed | O78: =VALUE(RIGHT(F78,1)) -> 2
A79: V3.8.4 | B79: V3 Authorization Decisions | C79: V3.8 Quantity, Rate, and Quota | D79: Harness | E79: Each agent run shall have a maximum number of tool invocations, a maximum run duration, and a maximum model invocation cost, enforced by the platform. When a limit is reached, the run shall be aborted and the initiator or owner notified. | F79: L2 | H79: ✓ | I79: ✓ | J79: All platforms | K79: Not assessed | O79: =VALUE(RIGHT(F79,1)) -> 2
A80: V4.1.1 | B80: V4 Credentials and Egress Enforcement | C80: V4.1 Credential Custody and Injection | D80: Egress gateway | E80: Tokens and keys required to access downstream systems shall be held by the platform. Only placeholder credentials shall appear in platform-hosted execution environments, in the context, and in the model, except for the cases specified in V5.2.2. | F80: L1 | G80: ✓ | H80: ✓ | I80: ✓ | J80: All platforms | K80: Not assessed | O80: =VALUE(RIGHT(F80,1)) -> 1
A81: V4.1.2 | B81: V4 Credentials and Egress Enforcement | C81: V4.1 Credential Custody and Injection | D81: Egress gateway | E81: Each managed credential shall be bound to permitted target domain names and paths, and the gateway shall inject the real credential only when the target matches | F81: L1 | G81: ✓ | H81: ✓ | I81: ✓ | J81: All platforms | K81: Not assessed | O81: =VALUE(RIGHT(F81,1)) -> 1
A82: V4.1.3 | B82: V4 Credentials and Egress Enforcement | C82: V4.1 Credential Custody and Injection | D82: Egress gateway | E82: The gateway shall not inject credentials into URLs or query parameters. Authentication for non-HTTP protocols shall be completed by the gateway or a platform-side proxy, and credentials shall not enter the execution environment. | F82: L2 | H82: ✓ | I82: ✓ | J82: All platforms | K82: Not assessed | O82: =VALUE(RIGHT(F82,1)) -> 2
A83: V4.1.4 | B83: V4 Credentials and Egress Enforcement | C83: V4.1 Credential Custody and Injection | D83: Egress gateway | E83: Substitution requests whose target does not match shall be rejected and alerted | F83: L2 | H83: ✓ | I83: ✓ | J83: All platforms | K83: Not assessed | O83: =VALUE(RIGHT(F83,1)) -> 2
A84: V4.1.5 | B84: V4 Credentials and Egress Enforcement | C84: V4.1 Credential Custody and Injection | D84: Egress gateway | E84: Credentials echoed in downstream responses shall be stripped before the response is returned to the execution environment | F84: L2 | H84: ✓ | I84: ✓ | J84: All platforms | K84: Not assessed | O84: =VALUE(RIGHT(F84,1)) -> 2
A85: V4.1.6 | B85: V4 Credentials and Egress Enforcement | C85: V4.1 Credential Custody and Injection | D85: Egress gateway | E85: The platform shall provide a managed authorization flow (such as OAuth), so that users do not need to hand personal credentials or API keys directly to the agent | F85: L2 | H85: ✓ | I85: ✓ | J85: All platforms | K85: Not assessed | O85: =VALUE(RIGHT(F85,1)) -> 2
A86: V4.1.7 | B86: V4 Credentials and Egress Enforcement | C86: V4.1 Credential Custody and Injection | D86: Harness | E86: Credentials appearing in conversations and uploaded files shall be identified, and their writing into memory, output artifacts, or agent configuration shall be blocked | F86: L2 | H86: ✓ | I86: ✓ | J86: All platforms | K86: Not assessed | O86: =VALUE(RIGHT(F86,1)) -> 2
A87: V4.2.1 | B87: V4 Credentials and Egress Enforcement | C87: V4.2 Unified Egress | D87: Egress gateway | E87: All of an agent's access outside the execution environment shall pass only through the egress gateway | F87: L1 | G87: ✓ | H87: ✓ | I87: ✓ | J87: All platforms | K87: Not assessed | O87: =VALUE(RIGHT(F87,1)) -> 1
A88: V4.2.2 | B88: V4 Credentials and Egress Enforcement | C88: V4.2 Unified Egress | D88: Execution environment | E88: Network egress from the execution environment shall be denied by default, and only traffic to the egress gateway shall be allowed | F88: L1 | G88: ✓ | H88: ✓ | I88: ✓ | J88: All platforms | K88: Not assessed | O88: =VALUE(RIGHT(F88,1)) -> 1
A89: V4.2.3 | B89: V4 Credentials and Egress Enforcement | C89: V4.2 Unified Egress | D89: Downstream systems | E89: Internal network services and databases shall reject direct connections from the execution environment's network segment that bypass the gateway | F89: L1 | G89: ✓ | H89: ✓ | I89: ✓ | J89: All platforms | K89: Not assessed | O89: =VALUE(RIGHT(F89,1)) -> 1
A90: V4.2.4 | B90: V4 Credentials and Egress Enforcement | C90: V4.2 Unified Egress | D90: Execution environment | E90: Hard-coded credentials in the execution environment, agent configurations, and images shall be scanned periodically | F90: L2 | H90: ✓ | I90: ✓ | J90: All platforms | K90: Not assessed | O90: =VALUE(RIGHT(F90,1)) -> 2
A91: V4.2.5 | B91: V4 Credentials and Egress Enforcement | C91: V4.2 Unified Egress | D91: Management plane | E91: The platform shall maintain an inventory of registered downstream systems (addresses, owning systems, and data classification), against which the egress gateway distinguishes intra-enterprise access from outbound transfer | F91: L1 | G91: ✓ | H91: ✓ | I91: ✓ | J91: All platforms | K91: Not assessed | O91: =VALUE(RIGHT(F91,1)) -> 1
A92: V4.3.1 | B92: V4 Credentials and Egress Enforcement | C92: V4.3 Downstream Identity Propagation | D92: Egress gateway | E92: When accessing third-party SaaS, user-level authorization shall be obtained, either by the user completing OAuth authorization personally or by obtaining a user-level token from the enterprise IdP via token exchange. Application credentials shared across users shall not be used. | F92: L1 | G92: ✓ | H92: ✓ | I92: ✓ | J92: All platforms | K92: Not assessed | O92: =VALUE(RIGHT(F92,1)) -> 1
A93: V4.3.2 | B93: V4 Credentials and Egress Enforcement | C93: V4.3 Downstream Identity Propagation | D93: Egress gateway | E93: When a user revokes authorization, the platform shall immediately stop using the corresponding credential | F93: L2 | H93: ✓ | I93: ✓ | J93: All platforms | K93: Not assessed | O93: =VALUE(RIGHT(F93,1)) -> 2
A94: V4.3.3 | B94: V4 Credentials and Egress Enforcement | C94: V4.3 Downstream Identity Propagation | D94: Identity layer | E94: When a downstream system supports token exchange, a user-level short-lived token shall be obtained through the enterprise IdP per RFC 8693, or through ID-JAG based on RFC 8693 and RFC 7523 | F94: L2 | H94: ✓ | I94: ✓ | J94: All platforms | K94: Not assessed | O94: =VALUE(RIGHT(F94,1)) -> 2
A95: V4.4.1 | B95: V4 Credentials and Egress Enforcement | C95: V4.4 Legacy Systems with Static Credentials | D95: Egress gateway | E95: Shared secrets of legacy systems shall be held by the platform and shall not be distributed to the execution environment | F95: L1 | G95: ✓ | H95: ✓ | I95: ✓ | J95: Platforms with downstream systems that support only shared static credentials | K95: Not assessed | O95: =VALUE(RIGHT(F95,1)) -> 1
A96: V4.4.2 | B96: V4 Credentials and Egress Enforcement | C96: V4.4 Legacy Systems with Static Credentials | D96: Egress gateway | E96: The gateway shall make user-level authorization decisions at the interface and operation levels to compensate for the lack of user-level authorization in the downstream system | F96: L1 | G96: ✓ | H96: ✓ | I96: ✓ | J96: Platforms with downstream systems that support only shared static credentials | K96: Not assessed | O96: =VALUE(RIGHT(F96,1)) -> 1
A97: V4.4.3 | B97: V4 Credentials and Egress Enforcement | C97: V4.4 Legacy Systems with Static Credentials | D97: Egress gateway | E97: The gateway shall attach a signed user identity to downstream requests so that downstream systems can verify it and progressively adopt user-level authorization | F97: L2 | H97: ✓ | I97: ✓ | J97: Platforms with downstream systems that support only shared static credentials | K97: Not assessed | O97: =VALUE(RIGHT(F97,1)) -> 2
A98: V4.4.4 | B98: V4 Credentials and Egress Enforcement | C98: V4.4 Legacy Systems with Static Credentials | D98: Management plane | E98: Downstream systems for which the gateway makes user-level authorization decisions on their behalf shall be registered and included in periodic review | F98: L2 | H98: ✓ | I98: ✓ | J98: Platforms with downstream systems that support only shared static credentials | K98: Not assessed | O98: =VALUE(RIGHT(F98,1)) -> 2
A99: V4.5.1 | B99: V4 Credentials and Egress Enforcement | C99: V4.5 MCP Invocation | D99: Egress gateway | E99: Requests to remote MCP servers shall pass through the egress gateway and carry the user identity | F99: L2 | H99: ✓ | I99: ✓ | J99: Platforms that support MCP | K99: Not assessed | O99: =VALUE(RIGHT(F99,1)) -> 2
A100: V4.5.2 | B100: V4 Credentials and Egress Enforcement | C100: V4.5 MCP Invocation | D100: Downstream systems | E100: MCP servers built or hosted by the platform shall not hold long-term credentials shared by all users | F100: L2 | H100: ✓ | I100: ✓ | J100: Platforms that support MCP | K100: Not assessed | O100: =VALUE(RIGHT(F100,1)) -> 2
...

Sheet Summary
A1: Assessment Progress
A2: Figures are calculated live by formulas from “Assessment Sheet”. Items within a target level = all items at that level and below; conformance rate = met ÷ (items − not applicable); not assessed counts as unmet.
A4: Target Level | B4: Items | C4: Met | D4: Partially Met | E4: Unmet | F4: Not applicable | G4: Not assessed | H4: Conformance Rate | I4: Result
A5: Reach L1 | B5: =COUNTIFS('Assessment Sheet'!$O$2:$O$241,"<=1") -> 90 | C5: =COUNTIFS('Assessment Sheet'!$O$2:$O$241,"<=1",'Assessment Sheet'!$K$2:$K$241,"Met") -> 0 | D5: =COUNTIFS('Assessment Sheet'!$O$2:$O$241,"<=1",'Assessment Sheet'!$K$2:$K$241,"Partially Met") -> 0 | E5: =COUNTIFS('Assessment Sheet'!$O$2:$O$241,"<=1",'Assessment Sheet'!$K$2:$K$241,"Unmet") -> 0 | F5: =COUNTIFS('Assessment Sheet'!$O$2:$O$241,"<=1",'Assessment Sheet'!$K$2:$K$241,"Not applicable") -> 0 | G5: =B5-SUM(C5:F5) -> 90 | H5: =IF(B5-F5=0,"—",C5/(B5-F5)) -> 0 | I5: =IF(C5=B5-F5,"Reached","Not reached") -> Not reached
A6: Reach L2 | B6: =COUNTIFS('Assessment Sheet'!$O$2:$O$241,"<=2") -> 227 | C6: =COUNTIFS('Assessment Sheet'!$O$2:$O$241,"<=2",'Assessment Sheet'!$K$2:$K$241,"Met") -> 0 | D6: =COUNTIFS('Assessment Sheet'!$O$2:$O$241,"<=2",'Assessment Sheet'!$K$2:$K$241,"Partially Met") -> 0 | E6: =COUNTIFS('Assessment Sheet'!$O$2:$O$241,"<=2",'Assessment Sheet'!$K$2:$K$241,"Unmet") -> 0 | F6: =COUNTIFS('Assessment Sheet'!$O$2:$O$241,"<=2",'Assessment Sheet'!$K$2:$K$241,"Not applicable") -> 0 | G6: =B6-SUM(C6:F6) -> 227 | H6: =IF(B6-F6=0,"—",C6/(B6-F6)) -> 0 | I6: =IF(C6=B6-F6,"Reached","Not reached") -> Not reached
A7: Reach L3 | B7: =COUNTIFS('Assessment Sheet'!$O$2:$O$241,"<=3") -> 240 | C7: =COUNTIFS('Assessment Sheet'!$O$2:$O$241,"<=3",'Assessment Sheet'!$K$2:$K$241,"Met") -> 0 | D7: =COUNTIFS('Assessment Sheet'!$O$2:$O$241,"<=3",'Assessment Sheet'!$K$2:$K$241,"Partially Met") -> 0 | E7: =COUNTIFS('Assessment Sheet'!$O$2:$O$241,"<=3",'Assessment Sheet'!$K$2:$K$241,"Unmet") -> 0 | F7: =COUNTIFS('Assessment Sheet'!$O$2:$O$241,"<=3",'Assessment Sheet'!$K$2:$K$241,"Not applicable") -> 0 | G7: =B7-SUM(C7:F7) -> 240 | H7: =IF(B7-F7=0,"—",C7/(B7-F7)) -> 0 | I7: =IF(C7=B7-F7,"Reached","Not reached") -> Not reached
A10: The three tables below are calculated for this target level ▸ | B10: L2 | C10: (switch between L1 / L2 / L3 in the drop-down)
A12: 按架构组件
A13: 架构组件 | B13: L1 | C13: New in L2 | D13: New in L3 | E13: Total | F13: Items in target | G13: Met | H13: Partially Met | I13: Unmet | J13: Not applicable | K13: Not assessed | L13: Conformance Rate | M13: Achieved Level
A14: Identity layer | B14: =COUNTIFS('Assessment Sheet'!$D$2:$D$241,$A14,'Assessment Sheet'!$F$2:$F$241,"L1") -> 7 | C14: =COUNTIFS('Assessment Sheet'!$D$2:$D$241,$A14,'Assessment Sheet'!$F$2:$F$241,"L2") -> 12 | D14: =COUNTIFS('Assessment Sheet'!$D$2:$D$241,$A14,'Assessment Sheet'!$F$2:$F$241,"L3") -> 3 | E14: =SUM(B14:D14) -> 22 | F14: =COUNTIFS('Assessment Sheet'!$D$2:$D$241,$A14,'Assessment Sheet'!$O$2:$O$241,"<="&VALUE(RIGHT($B$10,1))) -> 19 | G14: =COUNTIFS('Assessment Sheet'!$D$2:$D$241,$A14,'Assessment Sheet'!$O$2:$O$241,"<="&VALUE(RIGHT($B$10,1)),'Assessment Sheet'!$K$2:$K$241,"Met") -> 0 | H14: =COUNTIFS('Assessment Sheet'!$D$2:$D$241,$A14,'Assessment Sheet'!$O$2:$O$241,"<="&VALUE(RIGHT($B$10,1)),'Assessment Sheet'!$K$2:$K$241,"Partially Met") -> 0 | I14: =COUNTIFS('Assessment Sheet'!$D$2:$D$241,$A14,'Assessment Sheet'!$O$2:$O$241,"<="&VALUE(RIGHT($B$10,1)),'Assessment Sheet'!$K$2:$K$241,"Unmet") -> 0 | J14: =COUNTIFS('Assessment Sheet'!$D$2:$D$241,$A14,'Assessment Sheet'!$O$2:$O$241,"<="&VALUE(RIGHT($B$10,1)),'Assessment Sheet'!$K$2:$K$241,"Not applicable") -> 0 | K14: =F14-SUM(G14:J14) -> 19 | L14: =IF(F14-J14=0,"—",G14/(F14-J14)) -> 0 | M14: =IF(COUNTIFS('Assessment Sheet'!$D$2:$D$241,$A14,'Assessment Sheet'!$O$2:$O$241,"<=1",'Assessment Sheet'!$K$2:$K$241,"<>Met",'Assessment Sheet'!$K$2:$K$241,"<>Not applicable")>0,"Below L1",IF(COUNTIFS('Assessment Sheet'!$D$2:$D$241,$A14,'Assessment Sheet'!$O$2:$O$241,"<=2",'Assessment Sheet'!$K$2:$K$241,"<>Met",'Assessment Sheet'!$K$2:$K$241,"<>Not applicable")>0,"L1",IF(COUNTIFS('Assessment Sheet'!$D$2:$D$241,$A14,'Assessment Sheet'!$O$2:$O$241,"<=3",'Assessment Sheet'!$K$2:$K$241,"<>Met",'Assessment Sheet'!$K$2:$K$241,"<>Not applicable")>0,"L2","L3"))) -> Below L1
A15: Interaction channel | B15: =COUNTIFS('Assessment Sheet'!$D$2:$D$241,$A15,'Assessment Sheet'!$F$2:$F$241,"L1") -> 8 | C15: =COUNTIFS('Assessment Sheet'!$D$2:$D$241,$A15,'Assessment Sheet'!$F$2:$F$241,"L2") -> 10 | D15: =COUNTIFS('Assessment Sheet'!$D$2:$D$241,$A15,'Assessment Sheet'!$F$2:$F$241,"L3") -> 0 | E15: =SUM(B15:D15) -> 18 | F15: =COUNTIFS('Assessment Sheet'!$D$2:$D$241,$A15,'Assessment Sheet'!$O$2:$O$241,"<="&VALUE(RIGHT($B$10,1))) -> 18 | G15: =COUNTIFS('Assessment Sheet'!$D$2:$D$241,$A15,'Assessment Sheet'!$O$2:$O$241,"<="&VALUE(RIGHT($B$10,1)),'Assessment Sheet'!$K$2:$K$241,"Met") -> 0 | H15: =COUNTIFS('Assessment Sheet'!$D$2:$D$241,$A15,'Assessment Sheet'!$O$2:$O$241,"<="&VALUE(RIGHT($B$10,1)),'Assessment Sheet'!$K$2:$K$241,"Partially Met") -> 0 | I15: =COUNTIFS('Assessment Sheet'!$D$2:$D$241,$A15,'Assessment Sheet'!$O$2:$O$241,"<="&VALUE(RIGHT($B$10,1)),'Assessment Sheet'!$K$2:$K$241,"Unmet") -> 0 | J15: =COUNTIFS('Assessment Sheet'!$D$2:$D$241,$A15,'Assessment Sheet'!$O$2:$O$241,"<="&VALUE(RIGHT($B$10,1)),'Assessment Sheet'!$K$2:$K$241,"Not applicable") -> 0 | K15: =F15-SUM(G15:J15) -> 18 | L15: =IF(F15-J15=0,"—",G15/(F15-J15)) -> 0 | M15: =IF(COUNTIFS('Assessment Sheet'!$D$2:$D$241,$A15,'Assessment Sheet'!$O$2:$O$241,"<=1",'Assessment Sheet'!$K$2:$K$241,"<>Met",'Assessment Sheet'!$K$2:$K$241,"<>Not applicable")>0,"Below L1",IF(COUNTIFS('Assessment Sheet'!$D$2:$D$241,$A15,'Assessment Sheet'!$O$2:$O$241,"<=2",'Assessment Sheet'!$K$2:$K$241,"<>Met",'Assessment Sheet'!$K$2:$K$241,"<>Not applicable")>0,"L1",IF(COUNTIFS('Assessment Sheet'!$D$2:$D$241,$A15,'Assessment Sheet'!$O$2:$O$241,"<=3",'Assessment Sheet'!$K$2:$K$241,"<>Met",'Assessment Sheet'!$K$2:$K$241,"<>Not applicable")>0,"L2","L3"))) -> Below L1
A16: Harness | B16: =COUNTIFS('Assessment Sheet'!$D$2:$D$241,$A16,'Assessment Sheet'!$F$2:$F$241,"L1") -> 18 | C16: =COUNTIFS('Assessment Sheet'!$D$2:$D$241,$A16,'Assessment Sheet'!$F$2:$F$241,"L2") -> 28 | D16: =COUNTIFS('Assessment Sheet'!$D$2:$D$241,$A16,'Assessment Sheet'!$F$2:$F$241,"L3") -> 2 | E16: =SUM(B16:D16) -> 48 | F16: =COUNTIFS('Assessment Sheet'!$D$2:$D$241,$A16,'Assessment Sheet'!$O$2:$O$241,"<="&VALUE(RIGHT($B$10,1))) -> 46 | G16: =COUNTIFS('Assessment Sheet'!$D$2:$D$241,$A16,'Assessment Sheet'!$O$2:$O$241,"<="&VALUE(RIGHT($B$10,1)),'Assessment Sheet'!$K$2:$K$241,"Met") -> 0 | H16: =COUNTIFS('Assessment Sheet'!$D$2:$D$241,$A16,'Assessment Sheet'!$O$2:$O$241,"<="&VALUE(RIGHT($B$10,1)),'Assessment Sheet'!$K$2:$K$241,"Partially Met") -> 0 | I16: =COUNTIFS('Assessment Sheet'!$D$2:$D$241,$A16,'Assessment Sheet'!$O$2:$O$241,"<="&VALUE(RIGHT($B$10,1)),'Assessment Sheet'!$K$2:$K$241,"Unmet") -> 0 | J16: =COUNTIFS('Assessment Sheet'!$D$2:$D$241,$A16,'Assessment Sheet'!$O$2:$O$241,"<="&VALUE(RIGHT($B$10,1)),'Assessment Sheet'!$K$2:$K$241,"Not applicable") -> 0 | K16: =F16-SUM(G16:J16) -> 46 | L16: =IF(F16-J16=0,"—",G16/(F16-J16)) -> 0 | M16: =IF(COUNTIFS('Assessment Sheet'!$D$2:$D$241,$A16,'Assessment Sheet'!$O$2:$O$241,"<=1",'Assessment Sheet'!$K$2:$K$241,"<>Met",'Assessment Sheet'!$K$2:$K$241,"<>Not applicable")>0,"Below L1",IF(COUNTIFS('Assessment Sheet'!$D$2:$D$241,$A16,'Assessment Sheet'!$O$2:$O$241,"<=2",'Assessment Sheet'!$K$2:$K$241,"<>Met",'Assessment Sheet'!$K$2:$K$241,"<>Not applicable")>0,"L1",IF(COUNTIFS('Assessment Sheet'!$D$2:$D$241,$A16,'Assessment Sheet'!$O$2:$O$241,"<=3",'Assessment Sheet'!$K$2:$K$241,"<>Met",'Assessment Sheet'!$K$2:$K$241,"<>Not applicable")>0,"L2","L3"))) -> Below L1
A17: Policy decision point | B17: =COUNTIFS('Assessment Sheet'!$D$2:$D$241,$A17,'Assessment Sheet'!$F$2:$F$241,"L1") -> 12 | C17: =COUNTIFS('Assessment Sheet'!$D$2:$D$241,$A17,'Assessment Sheet'!$F$2:$F$241,"L2") -> 12 | D17: =COUNTIFS('Assessment Sheet'!$D$2:$D$241,$A17,'Assessment Sheet'!$F$2:$F$241,"L3") -> 5 | E17: =SUM(B17:D17) -> 29 | F17: =COUNTIFS('Assessment Sheet'!$D$2:$D$241,$A17,'Assessment Sheet'!$O$2:$O$241,"<="&VALUE(RIGHT($B$10,1))) -> 24 | G17: =COUNTIFS('Assessment Sheet'!$D$2:$D$241,$A17,'Assessment Sheet'!$O$2:$O$241,"<="&VALUE(RIGHT($B$10,1)),'Assessment Sheet'!$K$2:$K$241,"Met") -> 0 | H17: =COUNTIFS('Assessment Sheet'!$D$2:$D$241,$A17,'Assessment Sheet'!$O$2:$O$241,"<="&VALUE(RIGHT($B$10,1)),'Assessment Sheet'!$K$2:$K$241,"Partially Met") -> 0 | I17: =COUNTIFS('Assessment Sheet'!$D$2:$D$241,$A17,'Assessment Sheet'!$O$2:$O$241,"<="&VALUE(RIGHT($B$10,1)),'Assessment Sheet'!$K$2:$K$241,"Unmet") -> 0 | J17: =COUNTIFS('Assessment Sheet'!$D$2:$D$241,$A17,'Assessment Sheet'!$O$2:$O$241,"<="&VALUE(RIGHT($B$10,1)),'Assessment Sheet'!$K$2:$K$241,"Not applicable") -> 0 | K17: =F17-SUM(G17:J17) -> 24 | L17: =IF(F17-J17=0,"—",G17/(F17-J17)) -> 0 | M17: =IF(COUNTIFS('Assessment Sheet'!$D$2:$D$241,$A17,'Assessment Sheet'!$O$2:$O$241,"<=1",'Assessment Sheet'!$K$2:$K$241,"<>Met",'Assessment Sheet'!$K$2:$K$241,"<>Not applicable")>0,"Below L1",IF(COUNTIFS('Assessment Sheet'!$D$2:$D$241,$A17,'Assessment Sheet'!$O$2:$O$241,"<=2",'Assessment Sheet'!$K$2:$K$241,"<>Met",'Assessment Sheet'!$K$2:$K$241,"<>Not applicable")>0,"L1",IF(COUNTIFS('Assessment Sheet'!$D$2:$D$241,$A17,'Assessment Sheet'!$O$2:$O$241,"<=3",'Assessment Sheet'!$K$2:$K$241,"<>Met",'Assessment Sheet'!$K$2:$K$241,"<>Not applicable")>0,"L2","L3"))) -> Below L1
A18: Egress gateway | B18: =COUNTIFS('Assessment Sheet'!$D$2:$D$241,$A18,'Assessment Sheet'!$F$2:$F$241,"L1") -> 16 | C18: =COUNTIFS('Assessment Sheet'!$D$2:$D$241,$A18,'Assessment Sheet'!$F$2:$F$241,"L2") -> 16 | D18: =COUNTIFS('Assessment Sheet'!$D$2:$D$241,$A18,'Assessment Sheet'!$F$2:$F$241,"L3") -> 0 | E18: =SUM(B18:D18) -> 32 | F18: =COUNTIFS('Assessment Sheet'!$D$2:$D$241,$A18,'Assessment Sheet'!$O$2:$O$241,"<="&VALUE(RIGHT($B$10,1))) -> 32 | G18: =COUNTIFS('Assessment Sheet'!$D$2:$D$241,$A18,'Assessment Sheet'!$O$2:$O$241,"<="&VALUE(RIGHT($B$10,1)),'Assessment Sheet'!$K$2:$K$241,"Met") -> 0 | H18: =COUNTIFS('Assessment Sheet'!$D$2:$D$241,$A18,'Assessment Sheet'!$O$2:$O$241,"<="&VALUE(RIGHT($B$10,1)),'Assessment Sheet'!$K$2:$K$241,"Partially Met") -> 0 | I18: =COUNTIFS('Assessment Sheet'!$D$2:$D$241,$A18,'Assessment Sheet'!$O$2:$O$241,"<="&VALUE(RIGHT($B$10,1)),'Assessment Sheet'!$K$2:$K$241,"Unmet") -> 0 | J18: =COUNTIFS('Assessment Sheet'!$D$2:$D$241,$A18,'Assessment Sheet'!$O$2:$O$241,"<="&VALUE(RIGHT($B$10,1)),'Assessment Sheet'!$K$2:$K$241,"Not applicable") -> 0 | K18: =F18-SUM(G18:J18) -> 32 | L18: =IF(F18-J18=0,"—",G18/(F18-J18)) -> 0 | M18: =IF(COUNTIFS('Assessment Sheet'!$D$2:$D$241,$A18,'Assessment Sheet'!$O$2:$O$241,"<=1",'Assessment Sheet'!$K$2:$K$241,"<>Met",'Assessment Sheet'!$K$2:$K$241,"<>Not applicable")>0,"Below L1",IF(COUNTIFS('Assessment Sheet'!$D$2:$D$241,$A18,'Assessment Sheet'!$O$2:$O$241,"<=2",'Assessment Sheet'!$K$2:$K$241,"<>Met",'Assessment Sheet'!$K$2:$K$241,"<>Not applicable")>0,"L1",IF(COUNTIFS('Assessment Sheet'!$D$2:$D$241,$A18,'Assessment Sheet'!$O$2:$O$241,"<=3",'Assessment Sheet'!$K$2:$K$241,"<>Met",'Assessment Sheet'!$K$2:$K$241,"<>Not applicable")>0,"L2","L3"))) -> Below L1
A19: Downstream systems | B19: =COUNTIFS('Assessment Sheet'!$D$2:$D$241,$A19,'Assessment Sheet'!$F$2:$F$241,"L1") -> 2 | C19: =COUNTIFS('Assessment Sheet'!$D$2:$D$241,$A19,'Assessment Sheet'!$F$2:$F$241,"L2") -> 2 | D19: =COUNTIFS('Assessment Sheet'!$D$2:$D$241,$A19,'Assessment Sheet'!$F$2:$F$241,"L3") -> 0 | E19: =SUM(B19:D19) -> 4 | F19: =COUNTIFS('Assessment Sheet'!$D$2:$D$241,$A19,'Assessment Sheet'!$O$2:$O$241,"<="&VALUE(RIGHT($B$10,1))) -> 4 | G19: =COUNTIFS('Assessment Sheet'!$D$2:$D$241,$A19,'Assessment Sheet'!$O$2:$O$241,"<="&VALUE(RIGHT($B$10,1)),'Assessment Sheet'!$K$2:$K$241,"Met") -> 0 | H19: =COUNTIFS('Assessment Sheet'!$D$2:$D$241,$A19,'Assessment Sheet'!$O$2:$O$241,"<="&VALUE(RIGHT($B$10,1)),'Assessment Sheet'!$K$2:$K$241,"Partially Met") -> 0 | I19: =COUNTIFS('Assessment Sheet'!$D$2:$D$241,$A19,'Assessment Sheet'!$O$2:$O$241,"<="&VALUE(RIGHT($B$10,1)),'Assessment Sheet'!$K$2:$K$241,"Unmet") -> 0 | J19: =COUNTIFS('Assessment Sheet'!$D$2:$D$241,$A19,'Assessment Sheet'!$O$2:$O$241,"<="&VALUE(RIGHT($B$10,1)),'Assessment Sheet'!$K$2:$K$241,"Not applicable") -> 0 | K19: =F19-SUM(G19:J19) -> 4 | L19: =IF(F19-J19=0,"—",G19/(F19-J19)) -> 0 | M19: =IF(COUNTIFS('Assessment Sheet'!$D$2:$D$241,$A19,'Assessment Sheet'!$O$2:$O$241,"<=1",'Assessment Sheet'!$K$2:$K$241,"<>Met",'Assessment Sheet'!$K$2:$K$241,"<>Not applicable")>0,"Below L1",IF(COUNTIFS('Assessment Sheet'!$D$2:$D$241,$A19,'Assessment Sheet'!$O$2:$O$241,"<=2",'Assessment Sheet'!$K$2:$K$241,"<>Met",'Assessment Sheet'!$K$2:$K$241,"<>Not applicable")>0,"L1",IF(COUNTIFS('Assessment Sheet'!$D$2:$D$241,$A19,'Assessment Sheet'!$O$2:$O$241,"<=3",'Assessment Sheet'!$K$2:$K$241,"<>Met",'Assessment Sheet'!$K$2:$K$241,"<>Not applicable")>0,"L2","L3"))) -> Below L1
A20: Data layer | B20: =COUNTIFS('Assessment Sheet'!$D$2:$D$241,$A20,'Assessment Sheet'!$F$2:$F$241,"L1") -> 3 | C20: =COUNTIFS('Assessment Sheet'!$D$2:$D$241,$A20,'Assessment Sheet'!$F$2:$F$241,"L2") -> 11 | D20: =COUNTIFS('Assessment Sheet'!$D$2:$D$241,$A20,'Assessment Sheet'!$F$2:$F$241,"L3") -> 0 | E20: =SUM(B20:D20) -> 14 | F20: =COUNTIFS('Assessment Sheet'!$D$2:$D$241,$A20,'Assessment Sheet'!$O$2:$O$241,"<="&VALUE(RIGHT($B$10,1))) -> 14 | G20: =COUNTIFS('Assessment Sheet'!$D$2:$D$241,$A20,'Assessment Sheet'!$O$2:$O$241,"<="&VALUE(RIGHT($B$10,1)),'Assessment Sheet'!$K$2:$K$241,"Met") -> 0 | H20: =COUNTIFS('Assessment Sheet'!$D$2:$D$241,$A20,'Assessment Sheet'!$O$2:$O$241,"<="&VALUE(RIGHT($B$10,1)),'Assessment Sheet'!$K$2:$K$241,"Partially Met") -> 0 | I20: =COUNTIFS('Assessment Sheet'!$D$2:$D$241,$A20,'Assessment Sheet'!$O$2:$O$241,"<="&VALUE(RIGHT($B$10,1)),'Assessment Sheet'!$K$2:$K$241,"Unmet") -> 0 | J20: =COUNTIFS('Assessment Sheet'!$D$2:$D$241,$A20,'Assessment Sheet'!$O$2:$O$241,"<="&VALUE(RIGHT($B$10,1)),'Assessment Sheet'!$K$2:$K$241,"Not applicable") -> 0 | K20: =F20-SUM(G20:J20) -> 14 | L20: =IF(F20-J20=0,"—",G20/(F20-J20)) -> 0 | M20: =IF(COUNTIFS('Assessment Sheet'!$D$2:$D$241,$A20,'Assessment Sheet'!$O$2:$O$241,"<=1",'Assessment Sheet'!$K$2:$K$241,"<>Met",'Assessment Sheet'!$K$2:$K$241,"<>Not applicable")>0,"Below L1",IF(COUNTIFS('Assessment Sheet'!$D$2:$D$241,$A20,'Assessment Sheet'!$O$2:$O$241,"<=2",'Assessment Sheet'!$K$2:$K$241,"<>Met",'Assessment Sheet'!$K$2:$K$241,"<>Not applicable")>0,"L1",IF(COUNTIFS('Assessment Sheet'!$D$2:$D$241,$A20,'Assessment Sheet'!$O$2:$O$241,"<=3",'Assessment Sheet'!$K$2:$K$241,"<>Met",'Assessment Sheet'!$K$2:$K$241,"<>Not applicable")>0,"L2","L3"))) -> Below L1
A21: Execution environment | B21: =COUNTIFS('Assessment Sheet'!$D$2:$D$241,$A21,'Assessment Sheet'!$F$2:$F$241,"L1") -> 7 | C21: =COUNTIFS('Assessment Sheet'!$D$2:$D$241,$A21,'Assessment Sheet'!$F$2:$F$241,"L2") -> 6 | D21: =COUNTIFS('Assessment Sheet'!$D$2:$D$241,$A21,'Assessment Sheet'!$F$2:$F$241,"L3") -> 0 | E21: =SUM(B21:D21) -> 13 | F21: =COUNTIFS('Assessment Sheet'!$D$2:$D$241,$A21,'Assessment Sheet'!$O$2:$O$241,"<="&VALUE(RIGHT($B$10,1))) -> 13 | G21: =COUNTIFS('Assessment Sheet'!$D$2:$D$241,$A21,'Assessment Sheet'!$O$2:$O$241,"<="&VALUE(RIGHT($B$10,1)),'Assessment Sheet'!$K$2:$K$241,"Met") -> 0 | H21: =COUNTIFS('Assessment Sheet'!$D$2:$D$241,$A21,'Assessment Sheet'!$O$2:$O$241,"<="&VALUE(RIGHT($B$10,1)),'Assessment Sheet'!$K$2:$K$241,"Partially Met") -> 0 | I21: =COUNTIFS('Assessment Sheet'!$D$2:$D$241,$A21,'Assessment Sheet'!$O$2:$O$241,"<="&VALUE(RIGHT($B$10,1)),'Assessment Sheet'!$K$2:$K$241,"Unmet") -> 0 | J21: =COUNTIFS('Assessment Sheet'!$D$2:$D$241,$A21,'Assessment Sheet'!$O$2:$O$241,"<="&VALUE(RIGHT($B$10,1)),'Assessment Sheet'!$K$2:$K$241,"Not applicable") -> 0 | K21: =F21-SUM(G21:J21) -> 13 | L21: =IF(F21-J21=0,"—",G21/(F21-J21)) -> 0 | M21: =IF(COUNTIFS('Assessment Sheet'!$D$2:$D$241,$A21,'Assessment Sheet'!$O$2:$O$241,"<=1",'Assessment Sheet'!$K$2:$K$241,"<>Met",'Assessment Sheet'!$K$2:$K$241,"<>Not applicable")>0,"Below L1",IF(COUNTIFS('Assessment Sheet'!$D$2:$D$241,$A21,'Assessment Sheet'!$O$2:$O$241,"<=2",'Assessment Sheet'!$K$2:$K$241,"<>Met",'Assessment Sheet'!$K$2:$K$241,"<>Not applicable")>0,"L1",IF(COUNTIFS('Assessment Sheet'!$D$2:$D$241,$A21,'Assessment Sheet'!$O$2:$O$241,"<=3",'Assessment Sheet'!$K$2:$K$241,"<>Met",'Assessment Sheet'!$K$2:$K$241,"<>Not applicable")>0,"L2","L3"))) -> Below L1
A22: Management plane | B22: =COUNTIFS('Assessment Sheet'!$D$2:$D$241,$A22,'Assessment Sheet'!$F$2:$F$241,"L1") -> 13 | C22: =COUNTIFS('Assessment Sheet'!$D$2:$D$241,$A22,'Assessment Sheet'!$F$2:$F$241,"L2") -> 26 | D22: =COUNTIFS('Assessment Sheet'!$D$2:$D$241,$A22,'Assessment Sheet'!$F$2:$F$241,"L3") -> 1 | E22: =SUM(B22:D22) -> 40 | F22: =COUNTIFS('Assessment Sheet'!$D$2:$D$241,$A22,'Assessment Sheet'!$O$2:$O$241,"<="&VALUE(RIGHT($B$10,1))) -> 39 | G22: =COUNTIFS('Assessment Sheet'!$D$2:$D$241,$A22,'Assessment Sheet'!$O$2:$O$241,"<="&VALUE(RIGHT($B$10,1)),'Assessment Sheet'!$K$2:$K$241,"Met") -> 0 | H22: =COUNTIFS('Assessment Sheet'!$D$2:$D$241,$A22,'Assessment Sheet'!$O$2:$O$241,"<="&VALUE(RIGHT($B$10,1)),'Assessment Sheet'!$K$2:$K$241,"Partially Met") -> 0 | I22: =COUNTIFS('Assessment Sheet'!$D$2:$D$241,$A22,'Assessment Sheet'!$O$2:$O$241,"<="&VALUE(RIGHT($B$10,1)),'Assessment Sheet'!$K$2:$K$241,"Unmet") -> 0 | J22: =COUNTIFS('Assessment Sheet'!$D$2:$D$241,$A22,'Assessment Sheet'!$O$2:$O$241,"<="&VALUE(RIGHT($B$10,1)),'Assessment Sheet'!$K$2:$K$241,"Not applicable") -> 0 | K22: =F22-SUM(G22:J22) -> 39 | L22: =IF(F22-J22=0,"—",G22/(F22-J22)) -> 0 | M22: =IF(COUNTIFS('Assessment Sheet'!$D$2:$D$241,$A22,'Assessment Sheet'!$O$2:$O$241,"<=1",'Assessment Sheet'!$K$2:$K$241,"<>Met",'Assessment Sheet'!$K$2:$K$241,"<>Not applicable")>0,"Below L1",IF(COUNTIFS('Assessment Sheet'!$D$2:$D$241,$A22,'Assessment Sheet'!$O$2:$O$241,"<=2",'Assessment Sheet'!$K$2:$K$241,"<>Met",'Assessment Sheet'!$K$2:$K$241,"<>Not applicable")>0,"L1",IF(COUNTIFS('Assessment Sheet'!$D$2:$D$241,$A22,'Assessment Sheet'!$O$2:$O$241,"<=3",'Assessment Sheet'!$K$2:$K$241,"<>Met",'Assessment Sheet'!$K$2:$K$241,"<>Not applicable")>0,"L2","L3"))) -> Below L1
A23: Audit | B23: =COUNTIFS('Assessment Sheet'!$D$2:$D$241,$A23,'Assessment Sheet'!$F$2:$F$241,"L1") -> 4 | C23: =COUNTIFS('Assessment Sheet'!$D$2:$D$241,$A23,'Assessment Sheet'!$F$2:$F$241,"L2") -> 14 | D23: =COUNTIFS('Assessment Sheet'!$D$2:$D$241,$A23,'Assessment Sheet'!$F$2:$F$241,"L3") -> 2 | E23: =SUM(B23:D23) -> 20 | F23: =COUNTIFS('Assessment Sheet'!$D$2:$D$241,$A23,'Assessment Sheet'!$O$2:$O$241,"<="&VALUE(RIGHT($B$10,1))) -> 18 | G23: =COUNTIFS('Assessment Sheet'!$D$2:$D$241,$A23,'Assessment Sheet'!$O$2:$O$241,"<="&VALUE(RIGHT($B$10,1)),'Assessment Sheet'!$K$2:$K$241,"Met") -> 0 | H23: =COUNTIFS('Assessment Sheet'!$D$2:$D$241,$A23,'Assessment Sheet'!$O$2:$O$241,"<="&VALUE(RIGHT($B$10,1)),'Assessment Sheet'!$K$2:$K$241,"Partially Met") -> 0 | I23: =COUNTIFS('Assessment Sheet'!$D$2:$D$241,$A23,'Assessment Sheet'!$O$2:$O$241,"<="&VALUE(RIGHT($B$10,1)),'Assessment Sheet'!$K$2:$K$241,"Unmet") -> 0 | J23: =COUNTIFS('Assessment Sheet'!$D$2:$D$241,$A23,'Assessment Sheet'!$O$2:$O$241,"<="&VALUE(RIGHT($B$10,1)),'Assessment Sheet'!$K$2:$K$241,"Not applicable") -> 0 | K23: =F23-SUM(G23:J23) -> 18 | L23: =IF(F23-J23=0,"—",G23/(F23-J23)) -> 0 | M23: =IF(COUNTIFS('Assessment Sheet'!$D$2:$D$241,$A23,'Assessment Sheet'!$O$2:$O$241,"<=1",'Assessment Sheet'!$K$2:$K$241,"<>Met",'Assessment Sheet'!$K$2:$K$241,"<>Not applicable")>0,"Below L1",IF(COUNTIFS('Assessment Sheet'!$D$2:$D$241,$A23,'Assessment Sheet'!$O$2:$O$241,"<=2",'Assessment Sheet'!$K$2:$K$241,"<>Met",'Assessment Sheet'!$K$2:$K$241,"<>Not applicable")>0,"L1",IF(COUNTIFS('Assessment Sheet'!$D$2:$D$241,$A23,'Assessment Sheet'!$O$2:$O$241,"<=3",'Assessment Sheet'!$K$2:$K$241,"<>Met",'Assessment Sheet'!$K$2:$K$241,"<>Not applicable")>0,"L2","L3"))) -> Below L1
A24: Total | B24: =SUM(B14:B23) -> 90 | C24: =SUM(C14:C23) -> 137 | D24: =SUM(D14:D23) -> 13 | E24: =SUM(E14:E23) -> 240 | F24: =SUM(F14:F23) -> 227 | G24: =SUM(G14:G23) -> 0 | H24: =SUM(H14:H23) -> 0 | I24: =SUM(I14:I23) -> 0 | ... K24: =SUM(K14:K23) -> 227 | L24: =IF(F24-J24=0,"—",G24/(F24-J24)) -> 0 | M24: =IF(COUNTIFS('Assessment Sheet'!$O$2:$O$241,"<=1",'Assessment Sheet'!$K$2:$K$241,"<>Met",'Assessment Sheet'!$K$2:$K$241,"<>Not applicable")>0,"Below L1",IF(COUNTIFS('Assessment Sheet'!$O$2:$O$241,"<=2",'Assessment Sheet'!$K$2:$K$241,"<>Met",'Assessment Sheet'!$K$2:$K$241,"<>Not applicable")>0,"L1",IF(COUNTIFS('Assessment Sheet'!$O$2:$O$241,"<=3",'Assessment Sheet'!$K$2:$K$241,"<>Met",'Assessment Sheet'!$K$2:$K$241,"<>Not applicable")>0,"L2","L3"))) -> Below L1
A27: By chapter
A28: Chapter | B28: L1 | C28: New in L2 | D28: New in L3 | E28: Total | F28: Items in target | G28: Met | H28: Partially Met | I28: Unmet | J28: Not applicable | K28: Not assessed | L28: Conformance Rate | M28: Achieved Level
A29: V1 Identity and Authentication | B29: =COUNTIFS('Assessment Sheet'!$B$2:$B$241,$A29,'Assessment Sheet'!$F$2:$F$241,"L1") -> 11 | C29: =COUNTIFS('Assessment Sheet'!$B$2:$B$241,$A29,'Assessment Sheet'!$F$2:$F$241,"L2") -> 11 | D29: =COUNTIFS('Assessment Sheet'!$B$2:$B$241,$A29,'Assessment Sheet'!$F$2:$F$241,"L3") -> 1 | E29: =SUM(B29:D29) -> 23 | F29: =COUNTIFS('Assessment Sheet'!$B$2:$B$241,$A29,'Assessment Sheet'!$O$2:$O$241,"<="&VALUE(RIGHT($B$10,1))) -> 22 | G29: =COUNTIFS('Assessment Sheet'!$B$2:$B$241,$A29,'Assessment Sheet'!$O$2:$O$241,"<="&VALUE(RIGHT($B$10,1)),'Assessment Sheet'!$K$2:$K$241,"Met") -> 0 | H29: =COUNTIFS('Assessment Sheet'!$B$2:$B$241,$A29,'Assessment Sheet'!$O$2:$O$241,"<="&VALUE(RIGHT($B$10,1)),'Assessment Sheet'!$K$2:$K$241,"Partially Met") -> 0 | I29: =COUNTIFS('Assessment Sheet'!$B$2:$B$241,$A29,'Assessment Sheet'!$O$2:$O$241,"<="&VALUE(RIGHT($B$10,1)),'Assessment Sheet'!$K$2:$K$241,"Unmet") -> 0 | J29: =COUNTIFS('Assessment Sheet'!$B$2:$B$241,$A29,'Assessment Sheet'!$O$2:$O$241,"<="&VALUE(RIGHT($B$10,1)),'Assessment Sheet'!$K$2:$K$241,"Not applicable") -> 0 | K29: =F29-SUM(G29:J29) -> 22 | L29: =IF(F29-J29=0,"—",G29/(F29-J29)) -> 0 | M29: =IF(COUNTIFS('Assessment Sheet'!$B$2:$B$241,$A29,'Assessment Sheet'!$O$2:$O$241,"<=1",'Assessment Sheet'!$K$2:$K$241,"<>Met",'Assessment Sheet'!$K$2:$K$241,"<>Not applicable")>0,"Below L1",IF(COUNTIFS('Assessment Sheet'!$B$2:$B$241,$A29,'Assessment Sheet'!$O$2:$O$241,"<=2",'Assessment Sheet'!$K$2:$K$241,"<>Met",'Assessment Sheet'!$K$2:$K$241,"<>Not applicable")>0,"L1",IF(COUNTIFS('Assessment Sheet'!$B$2:$B$241,$A29,'Assessment Sheet'!$O$2:$O$241,"<=3",'Assessment Sheet'!$K$2:$K$241,"<>Met",'Assessment Sheet'!$K$2:$K$241,"<>Not applicable")>0,"L2","L3"))) -> Below L1
A30: V2 Delegation and Effective Permissions | B30: =COUNTIFS('Assessment Sheet'!$B$2:$B$241,$A30,'Assessment Sheet'!$F$2:$F$241,"L1") -> 11 | C30: =COUNTIFS('Assessment Sheet'!$B$2:$B$241,$A30,'Assessment Sheet'!$F$2:$F$241,"L2") -> 14 | D30: =COUNTIFS('Assessment Sheet'!$B$2:$B$241,$A30,'Assessment Sheet'!$F$2:$F$241,"L3") -> 3 | E30: =SUM(B30:D30) -> 28 | F30: =COUNTIFS('Assessment Sheet'!$B$2:$B$241,$A30,'Assessment Sheet'!$O$2:$O$241,"<="&VALUE(RIGHT($B$10,1))) -> 25 | G30: =COUNTIFS('Assessment Sheet'!$B$2:$B$241,$A30,'Assessment Sheet'!$O$2:$O$241,"<="&VALUE(RIGHT($B$10,1)),'Assessment Sheet'!$K$2:$K$241,"Met") -> 0 | H30: =COUNTIFS('Assessment Sheet'!$B$2:$B$241,$A30,'Assessment Sheet'!$O$2:$O$241,"<="&VALUE(RIGHT($B$10,1)),'Assessment Sheet'!$K$2:$K$241,"Partially Met") -> 0 | I30: =COUNTIFS('Assessment Sheet'!$B$2:$B$241,$A30,'Assessment Sheet'!$O$2:$O$241,"<="&VALUE(RIGHT($B$10,1)),'Assessment Sheet'!$K$2:$K$241,"Unmet") -> 0 | J30: =COUNTIFS('Assessment Sheet'!$B$2:$B$241,$A30,'Assessment Sheet'!$O$2:$O$241,"<="&VALUE(RIGHT($B$10,1)),'Assessment Sheet'!$K$2:$K$241,"Not applicable") -> 0 | K30: =F30-SUM(G30:J30) -> 25 | L30: =IF(F30-J30=0,"—",G30/(F30-J30)) -> 0 | M30: =IF(COUNTIFS('Assessment Sheet'!$B$2:$B$241,$A30,'Assessment Sheet'!$O$2:$O$241,"<=1",'Assessment Sheet'!$K$2:$K$241,"<>Met",'Assessment Sheet'!$K$2:$K$241,"<>Not applicable")>0,"Below L1",IF(COUNTIFS('Assessment Sheet'!$B$2:$B$241,$A30,'Assessment Sheet'!$O$2:$O$241,"<=2",'Assessment Sheet'!$K$2:$K$241,"<>Met",'Assessment Sheet'!$K$2:$K$241,"<>Not applicable")>0,"L1",IF(COUNTIFS('Assessment Sheet'!$B$2:$B$241,$A30,'Assessment Sheet'!$O$2:$O$241,"<=3",'Assessment Sheet'!$K$2:$K$241,"<>Met",'Assessment Sheet'!$K$2:$K$241,"<>Not applicable")>0,"L2","L3"))) -> Below L1
A31: V3 Authorization Decisions | B31: =COUNTIFS('Assessment Sheet'!$B$2:$B$241,$A31,'Assessment Sheet'!$F$2:$F$241,"L1") -> 9 | C31: =COUNTIFS('Assessment Sheet'!$B$2:$B$241,$A31,'Assessment Sheet'!$F$2:$F$241,"L2") -> 16 | D31: =COUNTIFS('Assessment Sheet'!$B$2:$B$241,$A31,'Assessment Sheet'!$F$2:$F$241,"L3") -> 2 | E31: =SUM(B31:D31) -> 27 | F31: =COUNTIFS('Assessment Sheet'!$B$2:$B$241,$A31,'Assessment Sheet'!$O$2:$O$241,"<="&VALUE(RIGHT($B$10,1))) -> 25 | G31: =COUNTIFS('Assessment Sheet'!$B$2:$B$241,$A31,'Assessment Sheet'!$O$2:$O$241,"<="&VALUE(RIGHT($B$10,1)),'Assessment Sheet'!$K$2:$K$241,"Met") -> 0 | H31: =COUNTIFS('Assessment Sheet'!$B$2:$B$241,$A31,'Assessment Sheet'!$O$2:$O$241,"<="&VALUE(RIGHT($B$10,1)),'Assessment Sheet'!$K$2:$K$241,"Partially Met") -> 0 | I31: =COUNTIFS('Assessment Sheet'!$B$2:$B$241,$A31,'Assessment Sheet'!$O$2:$O$241,"<="&VALUE(RIGHT($B$10,1)),'Assessment Sheet'!$K$2:$K$241,"Unmet") -> 0 | J31: =COUNTIFS('Assessment Sheet'!$B$2:$B$241,$A31,'Assessment Sheet'!$O$2:$O$241,"<="&VALUE(RIGHT($B$10,1)),'Assessment Sheet'!$K$2:$K$241,"Not applicable") -> 0 | K31: =F31-SUM(G31:J31) -> 25 | L31: =IF(F31-J31=0,"—",G31/(F31-J31)) -> 0 | M31: =IF(COUNTIFS('Assessment Sheet'!$B$2:$B$241,$A31,'Assessment Sheet'!$O$2:$O$241,"<=1",'Assessment Sheet'!$K$2:$K$241,"<>Met",'Assessment Sheet'!$K$2:$K$241,"<>Not applicable")>0,"Below L1",IF(COUNTIFS('Assessment Sheet'!$B$2:$B$241,$A31,'Assessment Sheet'!$O$2:$O$241,"<=2",'Assessment Sheet'!$K$2:$K$241,"<>Met",'Assessment Sheet'!$K$2:$K$241,"<>Not applicable")>0,"L1",IF(COUNTIFS('Assessment Sheet'!$B$2:$B$241,$A31,'Assessment Sheet'!$O$2:$O$241,"<=3",'Assessment Sheet'!$K$2:$K$241,"<>Met",'Assessment Sheet'!$K$2:$K$241,"<>Not applicable")>0,"L2","L3"))) -> Below L1
A32: V4 Credentials and Egress Enforcement | B32: =COUNTIFS('Assessment Sheet'!$B$2:$B$241,$A32,'Assessment Sheet'!$F$2:$F$241,"L1") -> 14 | C32: =COUNTIFS('Assessment Sheet'!$B$2:$B$241,$A32,'Assessment Sheet'!$F$2:$F$241,"L2") -> 18 | D32: =COUNTIFS('Assessment Sheet'!$B$2:$B$241,$A32,'Assessment Sheet'!$F$2:$F$241,"L3") -> 1 | E32: =SUM(B32:D32) -> 33 | F32: =COUNTIFS('Assessment Sheet'!$B$2:$B$241,$A32,'Assessment Sheet'!$O$2:$O$241,"<="&VALUE(RIGHT($B$10,1))) -> 32 | G32: =COUNTIFS('Assessment Sheet'!$B$2:$B$241,$A32,'Assessment Sheet'!$O$2:$O$241,"<="&VALUE(RIGHT($B$10,1)),'Assessment Sheet'!$K$2:$K$241,"Met") -> 0 | H32: =COUNTIFS('Assessment Sheet'!$B$2:$B$241,$A32,'Assessment Sheet'!$O$2:$O$241,"<="&VALUE(RIGHT($B$10,1)),'Assessment Sheet'!$K$2:$K$241,"Partially Met") -> 0 | I32: =COUNTIFS('Assessment Sheet'!$B$2:$B$241,$A32,'Assessment Sheet'!$O$2:$O$241,"<="&VALUE(RIGHT($B$10,1)),'Assessment Sheet'!$K$2:$K$241,"Unmet") -> 0 | J32: =COUNTIFS('Assessment Sheet'!$B$2:$B$241,$A32,'Assessment Sheet'!$O$2:$O$241,"<="&VALUE(RIGHT($B$10,1)),'Assessment Sheet'!$K$2:$K$241,"Not applicable") -> 0 | K32: =F32-SUM(G32:J32) -> 32 | L32: =IF(F32-J32=0,"—",G32/(F32-J32)) -> 0 | M32: =IF(COUNTIFS('Assessment Sheet'!$B$2:$B$241,$A32,'Assessment Sheet'!$O$2:$O$241,"<=1",'Assessment Sheet'!$K$2:$K$241,"<>Met",'Assessment Sheet'!$K$2:$K$241,"<>Not applicable")>0,"Below L1",IF(COUNTIFS('Assessment Sheet'!$B$2:$B$241,$A32,'Assessment Sheet'!$O$2:$O$241,"<=2",'Assessment Sheet'!$K$2:$K$241,"<>Met",'Assessment Sheet'!$K$2:$K$241,"<>Not applicable")>0,"L1",IF(COUNTIFS('Assessment Sheet'!$B$2:$B$241,$A32,'Assessment Sheet'!$O$2:$O$241,"<=3",'Assessment Sheet'!$K$2:$K$241,"<>Met",'Assessment Sheet'!$K$2:$K$241,"<>Not applicable")>0,"L2","L3"))) -> Below L1
A33: V5 Execution Isolation | B33: =COUNTIFS('Assessment Sheet'!$B$2:$B$241,$A33,'Assessment Sheet'!$F$2:$F$241,"L1") -> 16 | C33: =COUNTIFS('Assessment Sheet'!$B$2:$B$241,$A33,'Assessment Sheet'!$F$2:$F$241,"L2") -> 11 | D33: =COUNTIFS('Assessment Sheet'!$B$2:$B$241,$A33,'Assessment Sheet'!$F$2:$F$241,"L3") -> 0 | E33: =SUM(B33:D33) -> 27 | F33: =COUNTIFS('Assessment Sheet'!$B$2:$B$241,$A33,'Assessment Sheet'!$O$2:$O$241,"<="&VALUE(RIGHT($B$10,1))) -> 27 | G33: =COUNTIFS('Assessment Sheet'!$B$2:$B$241,$A33,'Assessment Sheet'!$O$2:$O$241,"<="&VALUE(RIGHT($B$10,1)),'Assessment Sheet'!$K$2:$K$241,"Met") -> 0 | H33: =COUNTIFS('Assessment Sheet'!$B$2:$B$241,$A33,'Assessment Sheet'!$O$2:$O$241,"<="&VALUE(RIGHT($B$10,1)),'Assessment Sheet'!$K$2:$K$241,"Partially Met") -> 0 | I33: =COUNTIFS('Assessment Sheet'!$B$2:$B$241,$A33,'Assessment Sheet'!$O$2:$O$241,"<="&VALUE(RIGHT($B$10,1)),'Assessment Sheet'!$K$2:$K$241,"Unmet") -> 0 | J33: =COUNTIFS('Assessment Sheet'!$B$2:$B$241,$A33,'Assessment Sheet'!$O$2:$O$241,"<="&VALUE(RIGHT($B$10,1)),'Assessment Sheet'!$K$2:$K$241,"Not applicable") -> 0 | K33: =F33-SUM(G33:J33) -> 27 | L33: =IF(F33-J33=0,"—",G33/(F33-J33)) -> 0 | M33: =IF(COUNTIFS('Assessment Sheet'!$B$2:$B$241,$A33,'Assessment Sheet'!$O$2:$O$241,"<=1",'Assessment Sheet'!$K$2:$K$241,"<>Met",'Assessment Sheet'!$K$2:$K$241,"<>Not applicable")>0,"Below L1",IF(COUNTIFS('Assessment Sheet'!$B$2:$B$241,$A33,'Assessment Sheet'!$O$2:$O$241,"<=2",'Assessment Sheet'!$K$2:$K$241,"<>Met",'Assessment Sheet'!$K$2:$K$241,"<>Not applicable")>0,"L1",IF(COUNTIFS('Assessment Sheet'!$B$2:$B$241,$A33,'Assessment Sheet'!$O$2:$O$241,"<=3",'Assessment Sheet'!$K$2:$K$241,"<>Met",'Assessment Sheet'!$K$2:$K$241,"<>Not applicable")>0,"L2","L3"))) -> Below L1
A34: V6 Context and Untrusted Input | B34: =COUNTIFS('Assessment Sheet'!$B$2:$B$241,$A34,'Assessment Sheet'!$F$2:$F$241,"L1") -> 4 | C34: =COUNTIFS('Assessment Sheet'!$B$2:$B$241,$A34,'Assessment Sheet'!$F$2:$F$241,"L2") -> 8 | D34: =COUNTIFS('Assessment Sheet'!$B$2:$B$241,$A34,'Assessment Sheet'!$F$2:$F$241,"L3") -> 1 | E34: =SUM(B34:D34) -> 13 | F34: =COUNTIFS('Assessment Sheet'!$B$2:$B$241,$A34,'Assessment Sheet'!$O$2:$O$241,"<="&VALUE(RIGHT($B$10,1))) -> 12 | G34: =COUNTIFS('Assessment Sheet'!$B$2:$B$241,$A34,'Assessment Sheet'!$O$2:$O$241,"<="&VALUE(RIGHT($B$10,1)),'Assessment Sheet'!$K$2:$K$241,"Met") -> 0 | H34: =COUNTIFS('Assessment Sheet'!$B$2:$B$241,$A34,'Assessment Sheet'!$O$2:$O$241,"<="&VALUE(RIGHT($B$10,1)),'Assessment Sheet'!$K$2:$K$241,"Partially Met") -> 0 | I34: =COUNTIFS('Assessment Sheet'!$B$2:$B$241,$A34,'Assessment Sheet'!$O$2:$O$241,"<="&VALUE(RIGHT($B$10,1)),'Assessment Sheet'!$K$2:$K$241,"Unmet") -> 0 | J34: =COUNTIFS('Assessment Sheet'!$B$2:$B$241,$A34,'Assessment Sheet'!$O$2:$O$241,"<="&VALUE(RIGHT($B$10,1)),'Assessment Sheet'!$K$2:$K$241,"Not applicable") -> 0 | K34: =F34-SUM(G34:J34) -> 12 | L34: =IF(F34-J34=0,"—",G34/(F34-J34)) -> 0 | M34: =IF(COUNTIFS('Assessment Sheet'!$B$2:$B$241,$A34,'Assessment Sheet'!$O$2:$O$241,"<=1",'Assessment Sheet'!$K$2:$K$241,"<>Met",'Assessment Sheet'!$K$2:$K$241,"<>Not applicable")>0,"Below L1",IF(COUNTIFS('Assessment Sheet'!$B$2:$B$241,$A34,'Assessment Sheet'!$O$2:$O$241,"<=2",'Assessment Sheet'!$K$2:$K$241,"<>Met",'Assessment Sheet'!$K$2:$K$241,"<>Not applicable")>0,"L1",IF(COUNTIFS('Assessment Sheet'!$B$2:$B$241,$A34,'Assessment Sheet'!$O$2:$O$241,"<=3",'Assessment Sheet'!$K$2:$K$241,"<>Met",'Assessment Sheet'!$K$2:$K$241,"<>Not applicable")>0,"L2","L3"))) -> Below L1
A35: V7 Output and Visibility | B35: =COUNTIFS('Assessment Sheet'!$B$2:$B$241,$A35,'Assessment Sheet'!$F$2:$F$241,"L1") -> 6 | C35: =COUNTIFS('Assessment Sheet'!$B$2:$B$241,$A35,'Assessment Sheet'!$F$2:$F$241,"L2") -> 12 | D35: =COUNTIFS('Assessment Sheet'!$B$2:$B$241,$A35,'Assessment Sheet'!$F$2:$F$241,"L3") -> 0 | E35: =SUM(B35:D35) -> 18 | F35: =COUNTIFS('Assessment Sheet'!$B$2:$B$241,$A35,'Assessment Sheet'!$O$2:$O$241,"<="&VALUE(RIGHT($B$10,1))) -> 18 | G35: =COUNTIFS('Assessment Sheet'!$B$2:$B$241,$A35,'Assessment Sheet'!$O$2:$O$241,"<="&VALUE(RIGHT($B$10,1)),'Assessment Sheet'!$K$2:$K$241,"Met") -> 0 | H35: =COUNTIFS('Assessment Sheet'!$B$2:$B$241,$A35,'Assessment Sheet'!$O$2:$O$241,"<="&VALUE(RIGHT($B$10,1)),'Assessment Sheet'!$K$2:$K$241,"Partially Met") -> 0 | I35: =COUNTIFS('Assessment Sheet'!$B$2:$B$241,$A35,'Assessment Sheet'!$O$2:$O$241,"<="&VALUE(RIGHT($B$10,1)),'Assessment Sheet'!$K$2:$K$241,"Unmet") -> 0 | J35: =COUNTIFS('Assessment Sheet'!$B$2:$B$241,$A35,'Assessment Sheet'!$O$2:$O$241,"<="&VALUE(RIGHT($B$10,1)),'Assessment Sheet'!$K$2:$K$241,"Not applicable") -> 0 | K35: =F35-SUM(G35:J35) -> 18 | L35: =IF(F35-J35=0,"—",G35/(F35-J35)) -> 0 | M35: =IF(COUNTIFS('Assessment Sheet'!$B$2:$B$241,$A35,'Assessment Sheet'!$O$2:$O$241,"<=1",'Assessment Sheet'!$K$2:$K$241,"<>Met",'Assessment Sheet'!$K$2:$K$241,"<>Not applicable")>0,"Below L1",IF(COUNTIFS('Assessment Sheet'!$B$2:$B$241,$A35,'Assessment Sheet'!$O$2:$O$241,"<=2",'Assessment Sheet'!$K$2:$K$241,"<>Met",'Assessment Sheet'!$K$2:$K$241,"<>Not applicable")>0,"L1",IF(COUNTIFS('Assessment Sheet'!$B$2:$B$241,$A35,'Assessment Sheet'!$O$2:$O$241,"<=3",'Assessment Sheet'!$K$2:$K$241,"<>Met",'Assessment Sheet'!$K$2:$K$241,"<>Not applicable")>0,"L2","L3"))) -> Below L1
A36: V8 Data, Memory, and Output Artifacts | B36: =COUNTIFS('Assessment Sheet'!$B$2:$B$241,$A36,'Assessment Sheet'!$F$2:$F$241,"L1") -> 5 | C36: =COUNTIFS('Assessment Sheet'!$B$2:$B$241,$A36,'Assessment Sheet'!$F$2:$F$241,"L2") -> 16 | D36: =COUNTIFS('Assessment Sheet'!$B$2:$B$241,$A36,'Assessment Sheet'!$F$2:$F$241,"L3") -> 1 | E36: =SUM(B36:D36) -> 22 | F36: =COUNTIFS('Assessment Sheet'!$B$2:$B$241,$A36,'Assessment Sheet'!$O$2:$O$241,"<="&VALUE(RIGHT($B$10,1))) -> 21 | G36: =COUNTIFS('Assessment Sheet'!$B$2:$B$241,$A36,'Assessment Sheet'!$O$2:$O$241,"<="&VALUE(RIGHT($B$10,1)),'Assessment Sheet'!$K$2:$K$241,"Met") -> 0 | H36: =COUNTIFS('Assessment Sheet'!$B$2:$B$241,$A36,'Assessment Sheet'!$O$2:$O$241,"<="&VALUE(RIGHT($B$10,1)),'Assessment Sheet'!$K$2:$K$241,"Partially Met") -> 0 | I36: =COUNTIFS('Assessment Sheet'!$B$2:$B$241,$A36,'Assessment Sheet'!$O$2:$O$241,"<="&VALUE(RIGHT($B$10,1)),'Assessment Sheet'!$K$2:$K$241,"Unmet") -> 0 | J36: =COUNTIFS('Assessment Sheet'!$B$2:$B$241,$A36,'Assessment Sheet'!$O$2:$O$241,"<="&VALUE(RIGHT($B$10,1)),'Assessment Sheet'!$K$2:$K$241,"Not applicable") -> 0 | K36: =F36-SUM(G36:J36) -> 21 | L36: =IF(F36-J36=0,"—",G36/(F36-J36)) -> 0 | M36: =IF(COUNTIFS('Assessment Sheet'!$B$2:$B$241,$A36,'Assessment Sheet'!$O$2:$O$241,"<=1",'Assessment Sheet'!$K$2:$K$241,"<>Met",'Assessment Sheet'!$K$2:$K$241,"<>Not applicable")>0,"Below L1",IF(COUNTIFS('Assessment Sheet'!$B$2:$B$241,$A36,'Assessment Sheet'!$O$2:$O$241,"<=2",'Assessment Sheet'!$K$2:$K$241,"<>Met",'Assessment Sheet'!$K$2:$K$241,"<>Not applicable")>0,"L1",IF(COUNTIFS('Assessment Sheet'!$B$2:$B$241,$A36,'Assessment Sheet'!$O$2:$O$241,"<=3",'Assessment Sheet'!$K$2:$K$241,"<>Met",'Assessment Sheet'!$K$2:$K$241,"<>Not applicable")>0,"L2","L3"))) -> Below L1
A37: V9 Lifecycle and Governance | B37: =COUNTIFS('Assessment Sheet'!$B$2:$B$241,$A37,'Assessment Sheet'!$F$2:$F$241,"L1") -> 9 | C37: =COUNTIFS('Assessment Sheet'!$B$2:$B$241,$A37,'Assessment Sheet'!$F$2:$F$241,"L2") -> 16 | D37: =COUNTIFS('Assessment Sheet'!$B$2:$B$241,$A37,'Assessment Sheet'!$F$2:$F$241,"L3") -> 1 | E37: =SUM(B37:D37) -> 26 | F37: =COUNTIFS('Assessment Sheet'!$B$2:$B$241,$A37,'Assessment Sheet'!$O$2:$O$241,"<="&VALUE(RIGHT($B$10,1))) -> 25 | G37: =COUNTIFS('Assessment Sheet'!$B$2:$B$241,$A37,'Assessment Sheet'!$O$2:$O$241,"<="&VALUE(RIGHT($B$10,1)),'Assessment Sheet'!$K$2:$K$241,"Met") -> 0 | H37: =COUNTIFS('Assessment Sheet'!$B$2:$B$241,$A37,'Assessment Sheet'!$O$2:$O$241,"<="&VALUE(RIGHT($B$10,1)),'Assessment Sheet'!$K$2:$K$241,"Partially Met") -> 0 | I37: =COUNTIFS('Assessment Sheet'!$B$2:$B$241,$A37,'Assessment Sheet'!$O$2:$O$241,"<="&VALUE(RIGHT($B$10,1)),'Assessment Sheet'!$K$2:$K$241,"Unmet") -> 0 | J37: =COUNTIFS('Assessment Sheet'!$B$2:$B$241,$A37,'Assessment Sheet'!$O$2:$O$241,"<="&VALUE(RIGHT($B$10,1)),'Assessment Sheet'!$K$2:$K$241,"Not applicable") -> 0 | K37: =F37-SUM(G37:J37) -> 25 | L37: =IF(F37-J37=0,"—",G37/(F37-J37)) -> 0 | M37: =IF(COUNTIFS('Assessment Sheet'!$B$2:$B$241,$A37,'Assessment Sheet'!$O$2:$O$241,"<=1",'Assessment Sheet'!$K$2:$K$241,"<>Met",'Assessment Sheet'!$K$2:$K$241,"<>Not applicable")>0,"Below L1",IF(COUNTIFS('Assessment Sheet'!$B$2:$B$241,$A37,'Assessment Sheet'!$O$2:$O$241,"<=2",'Assessment Sheet'!$K$2:$K$241,"<>Met",'Assessment Sheet'!$K$2:$K$241,"<>Not applicable")>0,"L1",IF(COUNTIFS('Assessment Sheet'!$B$2:$B$241,$A37,'Assessment Sheet'!$O$2:$O$241,"<=3",'Assessment Sheet'!$K$2:$K$241,"<>Met",'Assessment Sheet'!$K$2:$K$241,"<>Not applicable")>0,"L2","L3"))) -> Below L1
A38: V10 Audit, Detection, and Response | B38: =COUNTIFS('Assessment Sheet'!$B$2:$B$241,$A38,'Assessment Sheet'!$F$2:$F$241,"L1") -> 5 | C38: =COUNTIFS('Assessment Sheet'!$B$2:$B$241,$A38,'Assessment Sheet'!$F$2:$F$241,"L2") -> 15 | D38: =COUNTIFS('Assessment Sheet'!$B$2:$B$241,$A38,'Assessment Sheet'!$F$2:$F$241,"L3") -> 3 | E38: =SUM(B38:D38) -> 23 | F38: =COUNTIFS('Assessment Sheet'!$B$2:$B$241,$A38,'Assessment Sheet'!$O$2:$O$241,"<="&VALUE(RIGHT($B$10,1))) -> 20 | G38: =COUNTIFS('Assessment Sheet'!$B$2:$B$241,$A38,'Assessment Sheet'!$O$2:$O$241,"<="&VALUE(RIGHT($B$10,1)),'Assessment Sheet'!$K$2:$K$241,"Met") -> 0 | H38: =COUNTIFS('Assessment Sheet'!$B$2:$B$241,$A38,'Assessment Sheet'!$O$2:$O$241,"<="&VALUE(RIGHT($B$10,1)),'Assessment Sheet'!$K$2:$K$241,"Partially Met") -> 0 | I38: =COUNTIFS('Assessment Sheet'!$B$2:$B$241,$A38,'Assessment Sheet'!$O$2:$O$241,"<="&VALUE(RIGHT($B$10,1)),'Assessment Sheet'!$K$2:$K$241,"Unmet") -> 0 | J38: =COUNTIFS('Assessment Sheet'!$B$2:$B$241,$A38,'Assessment Sheet'!$O$2:$O$241,"<="&VALUE(RIGHT($B$10,1)),'Assessment Sheet'!$K$2:$K$241,"Not applicable") -> 0 | K38: =F38-SUM(G38:J38) -> 20 | L38: =IF(F38-J38=0,"—",G38/(F38-J38)) -> 0 | M38: =IF(COUNTIFS('Assessment Sheet'!$B$2:$B$241,$A38,'Assessment Sheet'!$O$2:$O$241,"<=1",'Assessment Sheet'!$K$2:$K$241,"<>Met",'Assessment Sheet'!$K$2:$K$241,"<>Not applicable")>0,"Below L1",IF(COUNTIFS('Assessment Sheet'!$B$2:$B$241,$A38,'Assessment Sheet'!$O$2:$O$241,"<=2",'Assessment Sheet'!$K$2:$K$241,"<>Met",'Assessment Sheet'!$K$2:$K$241,"<>Not applicable")>0,"L1",IF(COUNTIFS('Assessment Sheet'!$B$2:$B$241,$A38,'Assessment Sheet'!$O$2:$O$241,"<=3",'Assessment Sheet'!$K$2:$K$241,"<>Met",'Assessment Sheet'!$K$2:$K$241,"<>Not applicable")>0,"L2","L3"))) -> Below L1
A39: Total | B39: =SUM(B29:B38) -> 90 | C39: =SUM(C29:C38) -> 137 | D39: =SUM(D29:D38) -> 13 | E39: =SUM(E29:E38) -> 240 | F39: =SUM(F29:F38) -> 227 | G39: =SUM(G29:G38) -> 0 | H39: =SUM(H29:H38) -> 0 | I39: =SUM(I29:I38) -> 0 | ... K39: =SUM(K29:K38) -> 227 | L39: =IF(F39-J39=0,"—",G39/(F39-J39)) -> 0 | M39: =IF(COUNTIFS('Assessment Sheet'!$O$2:$O$241,"<=1",'Assessment Sheet'!$K$2:$K$241,"<>Met",'Assessment Sheet'!$K$2:$K$241,"<>Not applicable")>0,"Below L1",IF(COUNTIFS('Assessment Sheet'!$O$2:$O$241,"<=2",'Assessment Sheet'!$K$2:$K$241,"<>Met",'Assessment Sheet'!$K$2:$K$241,"<>Not applicable")>0,"L1",IF(COUNTIFS('Assessment Sheet'!$O$2:$O$241,"<=3",'Assessment Sheet'!$K$2:$K$241,"<>Met",'Assessment Sheet'!$K$2:$K$241,"<>Not applicable")>0,"L2","L3"))) -> Below L1
A42: Component × Chapter (item counts across all levels)
A43: Component | B43: V1 | C43: V2 | D43: V3 | E43: V4 | F43: V5 | G43: V6 | H43: V7 | I43: V8 | J43: V9 | K43: V10 | L43: Total
A44: Identity layer | B44: =COUNTIFS('Assessment Sheet'!$D$2:$D$241,$A44,'Assessment Sheet'!$B$2:$B$241,"V1 Identity and Authentication") -> 12 | C44: =COUNTIFS('Assessment Sheet'!$D$2:$D$241,$A44,'Assessment Sheet'!$B$2:$B$241,"V2 Delegation and Effective Permissions") -> 3 | D44: =COUNTIFS('Assessment Sheet'!$D$2:$D$241,$A44,'Assessment Sheet'!$B$2:$B$241,"V3 Authorization Decisions") -> 1 | E44: =COUNTIFS('Assessment Sheet'!$D$2:$D$241,$A44,'Assessment Sheet'!$B$2:$B$241,"V4 Credentials and Egress Enforcement") -> 4 | F44: =COUNTIFS('Assessment Sheet'!$D$2:$D$241,$A44,'Assessment Sheet'!$B$2:$B$241,"V5 Execution Isolation") -> 1 | G44: =COUNTIFS('Assessment Sheet'!$D$2:$D$241,$A44,'Assessment Sheet'!$B$2:$B$241,"V6 Context and Untrusted Input") -> 0 | H44: =COUNTIFS('Assessment Sheet'!$D$2:$D$241,$A44,'Assessment Sheet'!$B$2:$B$241,"V7 Output and Visibility") -> 0 | I44: =COUNTIFS('Assessment Sheet'!$D$2:$D$241,$A44,'Assessment Sheet'!$B$2:$B$241,"V8 Data, Memory, and Output Artifacts") -> 0 | J44: =COUNTIFS('Assessment Sheet'!$D$2:$D$241,$A44,'Assessment Sheet'!$B$2:$B$241,"V9 Lifecycle and Governance") -> 1 | K44: =COUNTIFS('Assessment Sheet'!$D$2:$D$241,$A44,'Assessment Sheet'!$B$2:$B$241,"V10 Audit, Detection, and Response") -> 0 | L44: =SUM(B44:K44) -> 22
A45: Interaction channel | B45: =COUNTIFS('Assessment Sheet'!$D$2:$D$241,$A45,'Assessment Sheet'!$B$2:$B$241,"V1 Identity and Authentication") -> 6 | C45: =COUNTIFS('Assessment Sheet'!$D$2:$D$241,$A45,'Assessment Sheet'!$B$2:$B$241,"V2 Delegation and Effective Permissions") -> 1 | D45: =COUNTIFS('Assessment Sheet'!$D$2:$D$241,$A45,'Assessment Sheet'!$B$2:$B$241,"V3 Authorization Decisions") -> 0 | E45: =COUNTIFS('Assessment Sheet'!$D$2:$D$241,$A45,'Assessment Sheet'!$B$2:$B$241,"V4 Credentials and Egress Enforcement") -> 0 | F45: =COUNTIFS('Assessment Sheet'!$D$2:$D$241,$A45,'Assessment Sheet'!$B$2:$B$241,"V5 Execution Isolation") -> 0 | G45: =COUNTIFS('Assessment Sheet'!$D$2:$D$241,$A45,'Assessment Sheet'!$B$2:$B$241,"V6 Context and Untrusted Input") -> 0 | H45: =COUNTIFS('Assessment Sheet'!$D$2:$D$241,$A45,'Assessment Sheet'!$B$2:$B$241,"V7 Output and Visibility") -> 10 | I45: =COUNTIFS('Assessment Sheet'!$D$2:$D$241,$A45,'Assessment Sheet'!$B$2:$B$241,"V8 Data, Memory, and Output Artifacts") -> 1 | J45: =COUNTIFS('Assessment Sheet'!$D$2:$D$241,$A45,'Assessment Sheet'!$B$2:$B$241,"V9 Lifecycle and Governance") -> 0 | K45: =COUNTIFS('Assessment Sheet'!$D$2:$D$241,$A45,'Assessment Sheet'!$B$2:$B$241,"V10 Audit, Detection, and Response") -> 0 | L45: =SUM(B45:K45) -> 18
A46: Harness | B46: =COUNTIFS('Assessment Sheet'!$D$2:$D$241,$A46,'Assessment Sheet'!$B$2:$B$241,"V1 Identity and Authentication") -> 1 | C46: =COUNTIFS('Assessment Sheet'!$D$2:$D$241,$A46,'Assessment Sheet'!$B$2:$B$241,"V2 Delegation and Effective Permissions") -> 2 | D46: =COUNTIFS('Assessment Sheet'!$D$2:$D$241,$A46,'Assessment Sheet'!$B$2:$B$241,"V3 Authorization Decisions") -> 14 | E46: =COUNTIFS('Assessment Sheet'!$D$2:$D$241,$A46,'Assessment Sheet'!$B$2:$B$241,"V4 Credentials and Egress Enforcement") -> 2 | F46: =COUNTIFS('Assessment Sheet'!$D$2:$D$241,$A46,'Assessment Sheet'!$B$2:$B$241,"V5 Execution Isolation") -> 11 | G46: =COUNTIFS('Assessment Sheet'!$D$2:$D$241,$A46,'Assessment Sheet'!$B$2:$B$241,"V6 Context and Untrusted Input") -> 10 | H46: =COUNTIFS('Assessment Sheet'!$D$2:$D$241,$A46,'Assessment Sheet'!$B$2:$B$241,"V7 Output and Visibility") -> 4 | I46: =COUNTIFS('Assessment Sheet'!$D$2:$D$241,$A46,'Assessment Sheet'!$B$2:$B$241,"V8 Data, Memory, and Output Artifacts") -> 3 | J46: =COUNTIFS('Assessment Sheet'!$D$2:$D$241,$A46,'Assessment Sheet'!$B$2:$B$241,"V9 Lifecycle and Governance") -> 0 | K46: =COUNTIFS('Assessment Sheet'!$D$2:$D$241,$A46,'Assessment Sheet'!$B$2:$B$241,"V10 Audit, Detection, and Response") -> 1 | L46: =SUM(B46:K46) -> 48
A47: Policy decision point | B47: =COUNTIFS('Assessment Sheet'!$D$2:$D$241,$A47,'Assessment Sheet'!$B$2:$B$241,"V1 Identity and Authentication") -> 1 | C47: =COUNTIFS('Assessment Sheet'!$D$2:$D$241,$A47,'Assessment Sheet'!$B$2:$B$241,"V2 Delegation and Effective Permissions") -> 15 | D47: =COUNTIFS('Assessment Sheet'!$D$2:$D$241,$A47,'Assessment Sheet'!$B$2:$B$241,"V3 Authorization Decisions") -> 8 | E47: =COUNTIFS('Assessment Sheet'!$D$2:$D$241,$A47,'Assessment Sheet'!$B$2:$B$241,"V4 Credentials and Egress Enforcement") -> 0 | F47: =COUNTIFS('Assessment Sheet'!$D$2:$D$241,$A47,'Assessment Sheet'!$B$2:$B$241,"V5 Execution Isolation") -> 0 | G47: =COUNTIFS('Assessment Sheet'!$D$2:$D$241,$A47,'Assessment Sheet'!$B$2:$B$241,"V6 Context and Untrusted Input") -> 0 | H47: =COUNTIFS('Assessment Sheet'!$D$2:$D$241,$A47,'Assessment Sheet'!$B$2:$B$241,"V7 Output and Visibility") -> 0 | I47: =COUNTIFS('Assessment Sheet'!$D$2:$D$241,$A47,'Assessment Sheet'!$B$2:$B$241,"V8 Data, Memory, and Output Artifacts") -> 1 | J47: =COUNTIFS('Assessment Sheet'!$D$2:$D$241,$A47,'Assessment Sheet'!$B$2:$B$241,"V9 Lifecycle and Governance") -> 1 | K47: =COUNTIFS('Assessment Sheet'!$D$2:$D$241,$A47,'Assessment Sheet'!$B$2:$B$241,"V10 Audit, Detection, and Response") -> 3 | L47: =SUM(B47:K47) -> 29
A48: Egress gateway | B48: =COUNTIFS('Assessment Sheet'!$D$2:$D$241,$A48,'Assessment Sheet'!$B$2:$B$241,"V1 Identity and Authentication") -> 1 | C48: =COUNTIFS('Assessment Sheet'!$D$2:$D$241,$A48,'Assessment Sheet'!$B$2:$B$241,"V2 Delegation and Effective Permissions") -> 2 | D48: =COUNTIFS('Assessment Sheet'!$D$2:$D$241,$A48,'Assessment Sheet'!$B$2:$B$241,"V3 Authorization Decisions") -> 2 | E48: =COUNTIFS('Assessment Sheet'!$D$2:$D$241,$A48,'Assessment Sheet'!$B$2:$B$241,"V4 Credentials and Egress Enforcement") -> 19 | F48: =COUNTIFS('Assessment Sheet'!$D$2:$D$241,$A48,'Assessment Sheet'!$B$2:$B$241,"V5 Execution Isolation") -> 2 | G48: =COUNTIFS('Assessment Sheet'!$D$2:$D$241,$A48,'Assessment Sheet'!$B$2:$B$241,"V6 Context and Untrusted Input") -> 0 | H48: =COUNTIFS('Assessment Sheet'!$D$2:$D$241,$A48,'Assessment Sheet'!$B$2:$B$241,"V7 Output and Visibility") -> 3 | I48: =COUNTIFS('Assessment Sheet'!$D$2:$D$241,$A48,'Assessment Sheet'!$B$2:$B$241,"V8 Data, Memory, and Output Artifacts") -> 3 | J48: =COUNTIFS('Assessment Sheet'!$D$2:$D$241,$A48,'Assessment Sheet'!$B$2:$B$241,"V9 Lifecycle and Governance") -> 0 | K48: =COUNTIFS('Assessment Sheet'!$D$2:$D$241,$A48,'Assessment Sheet'!$B$2:$B$241,"V10 Audit, Detection, and Response") -> 0 | L48: =SUM(B48:K48) -> 32
A49: Downstream systems | B49: =COUNTIFS('Assessment Sheet'!$D$2:$D$241,$A49,'Assessment Sheet'!$B$2:$B$241,"V1 Identity and Authentication") -> 1 | C49: =COUNTIFS('Assessment Sheet'!$D$2:$D$241,$A49,'Assessment Sheet'!$B$2:$B$241,"V2 Delegation and Effective Permissions") -> 0 | D49: =COUNTIFS('Assessment Sheet'!$D$2:$D$241,$A49,'Assessment Sheet'!$B$2:$B$241,"V3 Authorization Decisions") -> 0 | E49: =COUNTIFS('Assessment Sheet'!$D$2:$D$241,$A49,'Assessment Sheet'!$B$2:$B$241,"V4 Credentials and Egress Enforcement") -> 3 | F49: =COUNTIFS('Assessment Sheet'!$D$2:$D$241,$A49,'Assessment Sheet'!$B$2:$B$241,"V5 Execution Isolation") -> 0 | G49: =COUNTIFS('Assessment Sheet'!$D$2:$D$241,$A49,'Assessment Sheet'!$B$2:$B$241,"V6 Context and Untrusted Input") -> 0 | H49: =COUNTIFS('Assessment Sheet'!$D$2:$D$241,$A49,'Assessment Sheet'!$B$2:$B$241,"V7 Output and Visibility") -> 0 | I49: =COUNTIFS('Assessment Sheet'!$D$2:$D$241,$A49,'Assessment Sheet'!$B$2:$B$241,"V8 Data, Memory, and Output Artifacts") -> 0 | J49: =COUNTIFS('Assessment Sheet'!$D$2:$D$241,$A49,'Assessment Sheet'!$B$2:$B$241,"V9 Lifecycle and Governance") -> 0 | K49: =COUNTIFS('Assessment Sheet'!$D$2:$D$241,$A49,'Assessment Sheet'!$B$2:$B$241,"V10 Audit, Detection, and Response") -> 0 | L49: =SUM(B49:K49) -> 4
A50: Data layer | B50: =COUNTIFS('Assessment Sheet'!$D$2:$D$241,$A50,'Assessment Sheet'!$B$2:$B$241,"V1 Identity and Authentication") -> 0 | C50: =COUNTIFS('Assessment Sheet'!$D$2:$D$241,$A50,'Assessment Sheet'!$B$2:$B$241,"V2 Delegation and Effective Permissions") -> 0 | D50: =COUNTIFS('Assessment Sheet'!$D$2:$D$241,$A50,'Assessment Sheet'!$B$2:$B$241,"V3 Authorization Decisions") -> 0 | E50: =COUNTIFS('Assessment Sheet'!$D$2:$D$241,$A50,'Assessment Sheet'!$B$2:$B$241,"V4 Credentials and Egress Enforcement") -> 0 | F50: =COUNTIFS('Assessment Sheet'!$D$2:$D$241,$A50,'Assessment Sheet'!$B$2:$B$241,"V5 Execution Isolation") -> 0 | G50: =COUNTIFS('Assessment Sheet'!$D$2:$D$241,$A50,'Assessment Sheet'!$B$2:$B$241,"V6 Context and Untrusted Input") -> 0 | H50: =COUNTIFS('Assessment Sheet'!$D$2:$D$241,$A50,'Assessment Sheet'!$B$2:$B$241,"V7 Output and Visibility") -> 1 | I50: =COUNTIFS('Assessment Sheet'!$D$2:$D$241,$A50,'Assessment Sheet'!$B$2:$B$241,"V8 Data, Memory, and Output Artifacts") -> 13 | J50: =COUNTIFS('Assessment Sheet'!$D$2:$D$241,$A50,'Assessment Sheet'!$B$2:$B$241,"V9 Lifecycle and Governance") -> 0 | K50: =COUNTIFS('Assessment Sheet'!$D$2:$D$241,$A50,'Assessment Sheet'!$B$2:$B$241,"V10 Audit, Detection, and Response") -> 0 | L50: =SUM(B50:K50) -> 14
A51: Execution environment | B51: =COUNTIFS('Assessment Sheet'!$D$2:$D$241,$A51,'Assessment Sheet'!$B$2:$B$241,"V1 Identity and Authentication") -> 0 | C51: =COUNTIFS('Assessment Sheet'!$D$2:$D$241,$A51,'Assessment Sheet'!$B$2:$B$241,"V2 Delegation and Effective Permissions") -> 0 | D51: =COUNTIFS('Assessment Sheet'!$D$2:$D$241,$A51,'Assessment Sheet'!$B$2:$B$241,"V3 Authorization Decisions") -> 0 | E51: =COUNTIFS('Assessment Sheet'!$D$2:$D$241,$A51,'Assessment Sheet'!$B$2:$B$241,"V4 Credentials and Egress Enforcement") -> 3 | F51: =COUNTIFS('Assessment Sheet'!$D$2:$D$241,$A51,'Assessment Sheet'!$B$2:$B$241,"V5 Execution Isolation") -> 10 | G51: =COUNTIFS('Assessment Sheet'!$D$2:$D$241,$A51,'Assessment Sheet'!$B$2:$B$241,"V6 Context and Untrusted Input") -> 0 | H51: =COUNTIFS('Assessment Sheet'!$D$2:$D$241,$A51,'Assessment Sheet'!$B$2:$B$241,"V7 Output and Visibility") -> 0 | I51: =COUNTIFS('Assessment Sheet'!$D$2:$D$241,$A51,'Assessment Sheet'!$B$2:$B$241,"V8 Data, Memory, and Output Artifacts") -> 0 | J51: =COUNTIFS('Assessment Sheet'!$D$2:$D$241,$A51,'Assessment Sheet'!$B$2:$B$241,"V9 Lifecycle and Governance") -> 0 | K51: =COUNTIFS('Assessment Sheet'!$D$2:$D$241,$A51,'Assessment Sheet'!$B$2:$B$241,"V10 Audit, Detection, and Response") -> 0 | L51: =SUM(B51:K51) -> 13
A52: Management plane | B52: =COUNTIFS('Assessment Sheet'!$D$2:$D$241,$A52,'Assessment Sheet'!$B$2:$B$241,"V1 Identity and Authentication") -> 0 | C52: =COUNTIFS('Assessment Sheet'!$D$2:$D$241,$A52,'Assessment Sheet'!$B$2:$B$241,"V2 Delegation and Effective Permissions") -> 3 | D52: =COUNTIFS('Assessment Sheet'!$D$2:$D$241,$A52,'Assessment Sheet'!$B$2:$B$241,"V3 Authorization Decisions") -> 2 | E52: =COUNTIFS('Assessment Sheet'!$D$2:$D$241,$A52,'Assessment Sheet'!$B$2:$B$241,"V4 Credentials and Egress Enforcement") -> 2 | F52: =COUNTIFS('Assessment Sheet'!$D$2:$D$241,$A52,'Assessment Sheet'!$B$2:$B$241,"V5 Execution Isolation") -> 3 | G52: =COUNTIFS('Assessment Sheet'!$D$2:$D$241,$A52,'Assessment Sheet'!$B$2:$B$241,"V6 Context and Untrusted Input") -> 3 | H52: =COUNTIFS('Assessment Sheet'!$D$2:$D$241,$A52,'Assessment Sheet'!$B$2:$B$241,"V7 Output and Visibility") -> 0 | I52: =COUNTIFS('Assessment Sheet'!$D$2:$D$241,$A52,'Assessment Sheet'!$B$2:$B$241,"V8 Data, Memory, and Output Artifacts") -> 1 | J52: =COUNTIFS('Assessment Sheet'!$D$2:$D$241,$A52,'Assessment Sheet'!$B$2:$B$241,"V9 Lifecycle and Governance") -> 22 | K52: =COUNTIFS('Assessment Sheet'!$D$2:$D$241,$A52,'Assessment Sheet'!$B$2:$B$241,"V10 Audit, Detection, and Response") -> 4 | L52: =SUM(B52:K52) -> 40
A53: Audit | B53: =COUNTIFS('Assessment Sheet'!$D$2:$D$241,$A53,'Assessment Sheet'!$B$2:$B$241,"V1 Identity and Authentication") -> 1 | C53: =COUNTIFS('Assessment Sheet'!$D$2:$D$241,$A53,'Assessment Sheet'!$B$2:$B$241,"V2 Delegation and Effective Permissions") -> 2 | D53: =COUNTIFS('Assessment Sheet'!$D$2:$D$241,$A53,'Assessment Sheet'!$B$2:$B$241,"V3 Authorization Decisions") -> 0 | E53: =COUNTIFS('Assessment Sheet'!$D$2:$D$241,$A53,'Assessment Sheet'!$B$2:$B$241,"V4 Credentials and Egress Enforcement") -> 0 | F53: =COUNTIFS('Assessment Sheet'!$D$2:$D$241,$A53,'Assessment Sheet'!$B$2:$B$241,"V5 Execution Isolation") -> 0 | G53: =COUNTIFS('Assessment Sheet'!$D$2:$D$241,$A53,'Assessment Sheet'!$B$2:$B$241,"V6 Context and Untrusted Input") -> 0 | H53: =COUNTIFS('Assessment Sheet'!$D$2:$D$241,$A53,'Assessment Sheet'!$B$2:$B$241,"V7 Output and Visibility") -> 0 | I53: =COUNTIFS('Assessment Sheet'!$D$2:$D$241,$A53,'Assessment Sheet'!$B$2:$B$241,"V8 Data, Memory, and Output Artifacts") -> 0 | J53: =COUNTIFS('Assessment Sheet'!$D$2:$D$241,$A53,'Assessment Sheet'!$B$2:$B$241,"V9 Lifecycle and Governance") -> 2 | K53: =COUNTIFS('Assessment Sheet'!$D$2:$D$241,$A53,'Assessment Sheet'!$B$2:$B$241,"V10 Audit, Detection, and Response") -> 15 | L53: =SUM(B53:K53) -> 20
A54: Total | B54: =SUM(B44:B53) -> 23 | C54: =SUM(C44:C53) -> 28 | D54: =SUM(D44:D53) -> 27 | E54: =SUM(E44:E53) -> 33 | F54: =SUM(F44:F53) -> 27 | G54: =SUM(G44:G53) -> 13 | H54: =SUM(H44:H53) -> 18 | I54: =SUM(I44:I53) -> 22 | ... L54: =SUM(L44:L53) -> 240
A55: The darker the color, the more the chapter depends on this component for implementation.

Sheet Gap List
A1: Gap List (target level L2)
A2: Generated at export from the requirements within the target level whose status is neither “Met” nor “Not applicable”, sorted by level and ID. This sheet does not update automatically when you change statuses in the assessment sheet; export again to refresh it.
A3: ID | B3: Chapter | C3: Enforcement Component | D3: Requirement | E3: Minimum level | F3: Status | G3: Owner | H3: Planned Completion | I3: Evidence and Notes
A4: V1.1.1 | B4: V1 Identity and Authentication | C4: Identity layer | D4: The platform and all its channels shall allow login only through the enterprise IdP (OIDC or SAML) and shall not provide independent local accounts, except for the break-glass accounts specified in V10.5 | E4: L1 | F4: Not assessed
A5: V1.1.4 | B5: V1 Identity and Authentication | C5: Identity layer | D5: Credentials used to invoke agents through an API (such as API keys and personal access tokens) shall be bound to a specific user or non-human identity in the enterprise IdP, shall have an expiration time and a permission scope set, and shall be revoked automatically when the identity is disabled | E5: L1 | F5: Not assessed
A6: V1.2.1 | B6: V1 Identity and Authentication | C6: Interaction channel | D6: A channel account shall be bound to an enterprise identity through a one-time SSO login before it can invoke an agent | E6: L1 | F6: Not assessed
A7: V1.2.2 | B7: V1 Identity and Authentication | C7: Interaction channel | D7: The SSO binding result shall be the sole basis for identifying a channel account. Matching by nickname, display name, or email string is not permitted. The email channel follows V1.2.6. | E7: L1 | F7: Not assessed
A8: V1.2.6 | B8: V1 Identity and Authentication | C8: Interaction channel | D8: The email channel shall accept only email that passes DMARC verification (SPF or DKIM passing and aligned with the From domain). Senders from external domains shall not be able to trigger operations on behalf of a user. | E8: L1 | F8: Not assessed
A9: V1.3.1 | B9: V1 Identity and Authentication | C9: Identity layer | D9: Each agent shall have a unique identifier issued by the platform. The platform shall not accept identities self-reported by the agent. | E9: L1 | F9: Not assessed
A10: V1.3.2 | B10: V1 Identity and Authentication | C10: Identity layer | D10: An independent non-human identity shall be established in the enterprise directory for each autonomous agent. No employee's personal account shall be used. | E10: L1 | F10: Not assessed
A11: V1.4.1 | B11: V1 Identity and Authentication | C11: Identity layer | D11: The platform shall issue a short-lived workload identity to the execution instance of each session and bind it to that instance | E11: L1 | F11: Not assessed
A12: V1.4.2 | B12: V1 Identity and Authentication | C12: Harness | D12: The credentials of the workload identity shall be invisible to the model and shall not enter the context or tool return values | E12: L1 | F12: Not assessed
A13: V1.4.3 | B13: V1 Identity and Authentication | C13: Egress gateway | D13: The egress gateway shall determine the user and agent solely from the workload identity and shall ignore user or agent identifiers self-reported in the request | E13: L1 | F13: Not assessed
A14: V1.5.2 | B14: V1 Identity and Authentication | C14: Policy decision point | D14: External principals shall have access only to the workspaces and interfaces made available to them | E14: L1 | F14: Not assessed
A15: V2.1.1 | B15: V2 Delegation and Effective Permissions | C15: Egress gateway | D15: When the user is present, an agent accessing downstream systems shall carry the identity of the initiating user, and the downstream system shall make its authorization decision based on that user. Downstream systems that do not support user-level authorization decisions are handled under V4.4. | E15: L1 | F15: Not assessed
... A230: V10.6.2 | B230: V10 Audit, Detection, and Response | C230: Audit | D230: The platform shall be able to reconstruct all of an agent's operations within a specified period, by session or by delegation chain, to determine the scope of impact | E230: L2 | F230: Not assessed

Sheet Architecture View
A1: Architecture View
A2: Corresponds to Chapter 4 of the baseline. The enforcement component is the component primarily responsible for implementing or enforcing a requirement; when several components work together, the main one is listed.
A4: Component
A5: Component | C5: Responsibilities | D5: Trust Assumption | E5: L1 | F5: New in L2 | G5: New in L3
A6: Identity layer | C6: Enterprise IdP, directory, and SCIM; issues user, agent, and workload identities | D6: Trusted | E6: =COUNTIFS('Assessment Sheet'!$D$2:$D$241,$A6,'Assessment Sheet'!$F$2:$F$241,"L1") -> 7 | F6: =COUNTIFS('Assessment Sheet'!$D$2:$D$241,$A6,'Assessment Sheet'!$F$2:$F$241,"L2") -> 12 | G6: =COUNTIFS('Assessment Sheet'!$D$2:$D$241,$A6,'Assessment Sheet'!$F$2:$F$241,"L3") -> 3
A7: Interaction channel | C7: Web, IM, email, IDE, API, and other entry points; responsible for identity mapping and the visibility scope of output | D7: Trusted; content arriving through the channel is untrusted | E7: =COUNTIFS('Assessment Sheet'!$D$2:$D$241,$A7,'Assessment Sheet'!$F$2:$F$241,"L1") -> 8 | F7: =COUNTIFS('Assessment Sheet'!$D$2:$D$241,$A7,'Assessment Sheet'!$F$2:$F$241,"L2") -> 10 | G7: =COUNTIFS('Assessment Sheet'!$D$2:$D$241,$A7,'Assessment Sheet'!$F$2:$F$241,"L3") -> 0
A8: Harness | C8: Agent loop, context management, tool layer, security controls, orchestration, extension interfaces | D8: Trusted when platform-hosted; untrusted when running on employee endpoints, per V5.4 | E8: =COUNTIFS('Assessment Sheet'!$D$2:$D$241,$A8,'Assessment Sheet'!$F$2:$F$241,"L1") -> 18 | F8: =COUNTIFS('Assessment Sheet'!$D$2:$D$241,$A8,'Assessment Sheet'!$F$2:$F$241,"L2") -> 28 | G8: =COUNTIFS('Assessment Sheet'!$D$2:$D$241,$A8,'Assessment Sheet'!$F$2:$F$241,"L3") -> 2
A9: Policy decision point | C9: Computes effective permissions, determines risk levels, and decides whether approval is required | D9: Trusted | E9: =COUNTIFS('Assessment Sheet'!$D$2:$D$241,$A9,'Assessment Sheet'!$F$2:$F$241,"L1") -> 12 | F9: =COUNTIFS('Assessment Sheet'!$D$2:$D$241,$A9,'Assessment Sheet'!$F$2:$F$241,"L2") -> 12 | G9: =COUNTIFS('Assessment Sheet'!$D$2:$D$241,$A9,'Assessment Sheet'!$F$2:$F$241,"L3") -> 5
A10: Egress gateway | C10: Unified egress; injects credentials, validates targets, rate-limits, and revokes; the credential store belongs here | D10: Trusted | E10: =COUNTIFS('Assessment Sheet'!$D$2:$D$241,$A10,'Assessment Sheet'!$F$2:$F$241,"L1") -> 16 | F10: =COUNTIFS('Assessment Sheet'!$D$2:$D$241,$A10,'Assessment Sheet'!$F$2:$F$241,"L2") -> 16 | G10: =COUNTIFS('Assessment Sheet'!$D$2:$D$241,$A10,'Assessment Sheet'!$F$2:$F$241,"L3") -> 0
A11: Downstream systems | C11: SaaS, internal APIs, MCP servers, and databases being accessed | D11: Makes its own authorization decisions; returned content is untrusted | E11: =COUNTIFS('Assessment Sheet'!$D$2:$D$241,$A11,'Assessment Sheet'!$F$2:$F$241,"L1") -> 2 | F11: =COUNTIFS('Assessment Sheet'!$D$2:$D$241,$A11,'Assessment Sheet'!$F$2:$F$241,"L2") -> 2 | G11: =COUNTIFS('Assessment Sheet'!$D$2:$D$241,$A11,'Assessment Sheet'!$F$2:$F$241,"L3") -> 0
A12: Data layer | C12: Knowledge bases, RAG, memory, output artifacts | D12: Trusted; stored content may be poisoned and is handled as untrusted content | E12: =COUNTIFS('Assessment Sheet'!$D$2:$D$241,$A12,'Assessment Sheet'!$F$2:$F$241,"L1") -> 3 | F12: =COUNTIFS('Assessment Sheet'!$D$2:$D$241,$A12,'Assessment Sheet'!$F$2:$F$241,"L2") -> 11 | G12: =COUNTIFS('Assessment Sheet'!$D$2:$D$241,$A12,'Assessment Sheet'!$F$2:$F$241,"L3") -> 0
A13: Execution environment | C13: Executes code, commands, files, and browser operations | D13: Untrusted; may be compromised | E13: =COUNTIFS('Assessment Sheet'!$D$2:$D$241,$A13,'Assessment Sheet'!$F$2:$F$241,"L1") -> 7 | F13: =COUNTIFS('Assessment Sheet'!$D$2:$D$241,$A13,'Assessment Sheet'!$F$2:$F$241,"L2") -> 6 | G13: =COUNTIFS('Assessment Sheet'!$D$2:$D$241,$A13,'Assessment Sheet'!$F$2:$F$241,"L3") -> 0
A14: Management plane | C14: Agent registration, connectors, managed policies, lifecycle | D14: Trusted | E14: =COUNTIFS('Assessment Sheet'!$D$2:$D$241,$A14,'Assessment Sheet'!$F$2:$F$241,"L1") -> 13 | F14: =COUNTIFS('Assessment Sheet'!$D$2:$D$241,$A14,'Assessment Sheet'!$F$2:$F$241,"L2") -> 26 | G14: =COUNTIFS('Assessment Sheet'!$D$2:$D$241,$A14,'Assessment Sheet'!$F$2:$F$241,"L3") -> 1
A15: Audit | C15: Recording, retrieval, export, and retention, as well as detection and response | D15: Trusted | E15: =COUNTIFS('Assessment Sheet'!$D$2:$D$241,$A15,'Assessment Sheet'!$F$2:$F$241,"L1") -> 4 | F15: =COUNTIFS('Assessment Sheet'!$D$2:$D$241,$A15,'Assessment Sheet'!$F$2:$F$241,"L2") -> 14 | G15: =COUNTIFS('Assessment Sheet'!$D$2:$D$241,$A15,'Assessment Sheet'!$F$2:$F$241,"L3") -> 2
A17: The model enforces no controls: its output is only a request, and the related requirements fall on the harness.
A19: Checkpoints for a Single Tool Invocation
A20: Step | B20: Checkpoint | C20: What Happens | D20: Responsible Component | E20: Related Requirements
A21: 1 | B21: Entry authentication | C21: Map channel accounts to enterprise identities | D21: Interaction channel, identity layer | E21: V1.1、V1.2
A22: 2 | B22: Establish session | C22: Issue workload identity; determine user and agent | D22: Harness, identity layer | E22: V1.4
A23: 3 | B23: Assemble context | C23: Filter tool list, memory, and retrieval results by effective permissions | D23: Harness, data layer | E23: V3.3、V8.1、V8.3
A24: 4 | B24: Pre-invocation validation | C24: Policy check and risk classification before execution | D24: Harness, policy decision point | E24: V2.2、V3.1、V3.2
A25: 5 | B25: Human confirmation | C25: Generate approval from actual parameters; step-up authentication when necessary | D25: Harness, identity layer | E25: V3.4、V3.5
A26: 6 | B26: Egress execution | C26: Inject credentials through the gateway, validate target, rate-limit | D26: Egress gateway | E26: V4.1、V4.2、V3.8
A27: 7 | B27: Downstream authorization decision | C27: The downstream system makes an authorization decision based on the user identity passed when accessing on behalf of the user | D27: Downstream systems | E27: V2.1、V4.3、V4.4
A28: 8 | B28: Handle return | C28: Treat returned content as untrusted and mark its source | D28: Harness | E28: V6.1、V6.2
A29: 9 | B29: Output check | C29: Check recipient, sensitive data, and rendering risk | D29: Interaction channel, egress gateway | E29: V7.1、V7.4、V7.5
A30: 10 | B30: Full-process logging | C30: Each step is written to audit and traceable to the person, the agent, and the input source | D30: Audit | E30: V10.1

Sheet Notes
A1: Enterprise Agent Identity and Authorization Security Baseline Assessment Sheet
A2: Source Document | B2: Enterprise Agent Identity and Authorization Security Baseline v1.0 (2026-10-07). The document contains the full context of the requirements, terminology, architecture diagrams, threat model, and mapping appendices.
A3: Document Link | B3: https://github.com/teloa-ai/agent-baseline-assessor/blob/main/01-standard/en/baseline-v1.0.md
A4: Contents | B4: 240 requirements across 62 sections: 90 at L1, 137 more added at L2, and a further 13 added at L3.
A6: Assessment Information
A7: Assessment Subject
A8: Assessment Scope
A9: Assessor
A10: Assessment Date
A11: Target Level | B11: L2
A13: How to Fill In
A14: Fill in only the yellow columns | B14: The assessor fills in the four columns Status, Evidence and Notes, Owner, and Planned Completion. The other columns match the baseline and should not be changed here.
A15: Status | B15: Select from the drop-down: Not assessed, Met, Partially Met, Unmet, Not applicable. When an entire section does not apply because its applicability condition is not met, select “Not applicable” for every requirement in that section.
A16: Level | B16: L1 Baseline, L2 Standard, L3 Enhanced; a higher level includes all requirements of the lower levels. Reaching a level = all applicable requirements at that level and below are met.
A17: Back to the Web App | B17: This workbook can be imported on the “Data” page of the self-assessment web app; status, evidence, owner, and planned completion are filled back in by ID.
A19: Two Perspectives
A20: Chapter | B20: Answers “what is required”. V1 through V7 follow the order in which a single agent action occurs, and V8 through V10 are organized by data, agents, and audit that persist across sessions.
A21: Enforcement Component | B21: Answers “where is it implemented”, in the same order as the component table in section 4.2 of the baseline. Filter by component to assign items to the matching teams. See the “Architecture View” sheet for component definitions and checkpoints.
